Workbook

Sheet Dashboard
A1: Jet overflow charter business: dashboard
A2: Change the scenario on the Assumptions sheet (cell C3). All figures update.
A3: ="Scenario shown: "&Assumptions!$D$3 -> Scenario shown: Base
A5: Metric | C5: Value | D5: What it means
A6: Purchase price, Jet #1 | C6: =Assumptions!$F$7 -> 13500000
A7: Equity needed to launch | C7: ='Startup Budget'!C17 -> 3968625 | D7: Down payment + startup costs + reserve
A8: Aircraft loan | C8: ='Startup Budget'!C16 -> 10800000
A9: Mature-year EBITDA, one jet | C9: ='Unit Economics'!F25 -> 509050 | D9: Before debt
A10: Annual debt service, one jet | C10: =-'Unit Economics'!F29 -> 1204574.2
A11: Cash flow after debt, one jet | C11: ='Unit Economics'!F30 -> -695524.23 | D11: Negative = owners fund the gap
A12: Breakeven billable hours (EBITDA) | C12: ='Unit Economics'!F36 -> 425.09878
A13: Breakeven billable hours incl. debt | C13: ='Unit Economics'!F37 -> 838.9707 | D13: Key target for the management company
A14: Peak cumulative owner equity (10 yrs) | C14: =Exit!C20 -> 17667996 | D14: Total cash Henry and partners must fund
A15: Net exit proceeds | C15: =Exit!C15 -> 31694343
A16: Multiple on invested equity | C16: =Exit!C18 -> 1.7938844
A17: Equity IRR | C17: =Exit!C19 -> 0.094001978 | D17: Before owner tax effects
A18: Owned aircraft at exit | C18: =INDEX(Forecast!$C$11:$L$11,MATCH(Assumptions!$F$60,Forecast!$C$5:$L$5,0)) -> 3
A19: Third-party managed aircraft at exit | C19: =INDEX(Forecast!$C$16:$L$16,MATCH(Assumptions!$F$60,Forecast!$C$5:$L$5,0)) -> 12
A20: Revenue in exit year | C20: =INDEX(Forecast!$C$23:$L$23,MATCH(Assumptions!$F$60,Forecast!$C$5:$L$5,0)) -> 21202564
A21: EBITDA in exit year | C21: =INDEX(Forecast!$C$36:$L$36,MATCH(Assumptions!$F$60,Forecast!$C$5:$L$5,0)) -> 5580710.6
A23: Legend
A24: Blue text: input you can change
A25: Black text: formula
A26: Green text: link to another sheet
A27: Yellow fill: key lever
A28: All estimates must be verified with quotes from lenders, the management company, insurers and an aircraft broker.

Sheet Assumptions
A1: Assumptions: Citation Latitude overflow charter business
A2: Blue = input you can change. Yellow = key lever. Column F (Live) feeds the forecast based on the scenario selected in C3.
A3: Active scenario (1 = Downside, 2 = Base, 3 = Upside) | C3: 2 | D3: =INDEX({"Downside","Base","Upside"},$C$3) -> Base
A5: Assumption | B5: Unit | C5: Downside | D5: Base | E5: Upside | F5: Live | G5: Source / note
A6: Aircraft acquisition (per aircraft)
A7: Purchase price, used Citation Latitude (2016-2019) | B7: $ | C7: 15000000 | D7: 13500000 | E7: 12500000 | F7: =CHOOSE($C$3,C7,D7,E7) -> 13500000 | G7: AvBuyer/Aircraft Bluebook guide: 2020 Latitude ~$17.5M (May 2025), asking range $18.75-22.5M for newer units. Older 2016-2019 units assumed lower. VERIFY with a broker/JETNET before LOI.
A8: Annual change in price paid for later aircraft | B8: % | C8: 0 | D8: 0 | E8: 0 | F8: =CHOOSE($C$3,C8,D8,E8) -> 0 | G8: Assumes later purchases are similar-vintage aircraft at today's price. Adjust if the market moves.
A9: Pre-buy inspection (Textron service center) | B9: $ | C9: 85000 | D9: 75000 | E9: 60000 | F9: =CHOOSE($C$3,C9,D9,E9) -> 75000 | G9: Estimate; includes ferry to inspection facility and borescope.
A10: Closing legal, escrow, title, registration | B10: $ | C10: 60000 | D10: 50000 | E10: 40000 | F10: =CHOOSE($C$3,C10,D10,E10) -> 50000 | G10: Estimate.
A11: Part 135 onboarding, conformity, Wi-Fi/avionics updates | B11: $ | C11: 200000 | D11: 150000 | E11: 100000 | F11: =CHOOSE($C$3,C11,D11,E11) -> 150000 | G11: Adding aircraft to operator's certificate (conformity, manuals, OpSpecs), plus connectivity charter customers expect. Estimate.
A12: Cosmetic interior / paint refresh | B12: $ | C12: 350000 | D12: 250000 | E12: 150000 | F12: =CHOOSE($C$3,C12,D12,E12) -> 250000 | G12: Fractional customers expect fleet-standard cabins. Estimate.
A13: Initial crew training and hiring (per aircraft) | B13: $ | C13: 100000 | D13: 75000 | E13: 50000 | F13: =CHOOSE($C$3,C13,D13,E13) -> 75000 | G13: Type rating for new hires (CE-680A) and Part 135 initial. Estimate.
A14: Company formation, legal, accounting, insurance setup (once) | B14: $ | C14: 75000 | D14: 50000 | E14: 35000 | F14: =CHOOSE($C$3,C14,D14,E14) -> 50000 | G14: LLC formation, operating agreement, aviation counsel, CPA, insurance broker. Estimate.
A15: Financing
A16: Loan-to-value (debt share of purchase price) | B16: % | C16: 0.8 | D16: 0.8 | E16: 0.8 | F16: =CHOOSE($C$3,C16,D16,E16) -> 0.8 | G16: Henry: assume at least 80% debt. See 'Financing Scenarios' for 60-90%.
A17: Interest rate (fixed) | B17: % | C17: 0.08 | D17: 0.0725 | E17: 0.0675 | F17: =CHOOSE($C$3,C17,D17,E17) -> 0.0725 | G17: Advertised jet loan rates ~5.6-9% (Sep/Oct 2026 rate sheets); prime 7.00% (Oct 2026). flycraft.com/aircraft-financing/aircraft-loan-rates
A18: Amortization period | B18: years | C18: 15 | D18: 15 | E18: 20 | F18: =CHOOSE($C$3,C18,D18,E18) -> 15 | G18: Typical 10-20 yr amortization, often with a 5-7 yr balloon refinanced at the time. Model assumes refinance on same terms.
A19: Charter revenue (per owned aircraft)
A20: Billable revenue hours per aircraft at maturity | B20: hrs/yr | C20: 500 | D20: 600 | E20: 700 | F20: =CHOOSE($C$3,C20,D20,E20) -> 600 | G20: Includes billable repositioning. Dedicated fractional supplemental lift can run 800+ hrs; retail-only charter often 300-450.
A21: Months in revenue service in 2027 | B21: months | C21: 5 | D21: 6 | E21: 6 | F21: =CHOOSE($C$3,C21,D21,E21) -> 6 | G21: Henry: target revenue flying mid-2027.
A22: Utilization in first year of service (% of mature) | B22: % | C22: 0.5 | D22: 0.6 | E22: 0.7 | F22: =CHOOSE($C$3,C22,D22,E22) -> 0.6 | G22: Ramp while operator builds the aircraft into its overflow rotation.
A23: Utilization in second year (% of mature) | B23: % | C23: 0.8 | D23: 0.9 | E23: 1 | F23: =CHOOSE($C$3,C23,D23,E23) -> 0.9
A24: Share of hours flown as fractional / program overflow | B24: % | C24: 0.4 | D24: 0.5 | E24: 0.6 | F24: =CHOOSE($C$3,C24,D24,E24) -> 0.5 | G24: NetJets, Flexjet, jet card and membership programs. The rest is broker/retail charter.
A25: Wholesale rate, overflow / subcontract trips | B25: $/hr | C25: 6750 | D25: 7000 | E25: 7250 | F25: =CHOOSE($C$3,C25,D25,E25) -> 7000 | G25: Wholesale is below retail. NetJets' own midsize lift program retails $8,000-10,900/hr (SherpaReport). Estimate; get actual subcontract rates from the management company.
A26: Retail / broker charter rate | B26: $/hr | C26: 8000 | D26: 8500 | E26: 9000 | F26: =CHOOSE($C$3,C26,D26,E26) -> 8500 | G26: Excludes 7.5% federal excise tax (collected from the customer and remitted). Estimate.
A27: Annual charter rate growth | B27: % | C27: 0.02 | D27: 0.03 | E27: 0.035 | F27: =CHOOSE($C$3,C27,D27,E27) -> 0.03
A28: Unpaid positioning hours (% of billable) | B28: % | C28: 0.15 | D28: 0.1 | E28: 0.08 | F28: =CHOOSE($C$3,C28,D28,E28) -> 0.1 | G28: Denver base means some empty legs to the coasts. Estimate.
A29: Variable operating costs (per flight hour)
A30: Fuel burn | B30: gal/hr | C30: 285 | D30: 270 | E30: 260 | F30: =CHOOSE($C$3,C30,D30,E30) -> 270 | G30: Flycraft cites 315 gal/hr block (conservative); typical mission average lower.
A31: Jet-A price (contract/volume pricing) | B31: $/gal | C31: 7 | D31: 6.5 | E31: 6 | F31: =CHOOSE($C$3,C31,D31,E31) -> 6.5 | G31: Flycraft used $7.66/gal retail (Oct 2026). Contract fuel cards typically discount.
A32: Airframe maintenance and parts | B32: $/hr | C32: 850 | D32: 750 | E32: 650 | F32: =CHOOSE($C$3,C32,D32,E32) -> 750 | G32: Flycraft range $800-1,300/hr incl. unscheduled. Estimate.
A33: Engine program (2 x PW306D1, ESP) | B33: $/hr | C33: 700 | D33: 660 | E33: 620 | F33: =CHOOSE($C$3,C33,D33,E33) -> 660 | G33: Flycraft range $275-425 per engine per hour. Engines must be on program for resale value.
A34: APU program | B34: $/hr | C34: 100 | D34: 80 | E34: 70 | F34: =CHOOSE($C$3,C34,D34,E34) -> 80 | G34: Estimate.
A35: Crew travel, landing, handling fees (not rebilled) | B35: $/hr | C35: 500 | D35: 450 | E35: 400 | F35: =CHOOSE($C$3,C35,D35,E35) -> 450 | G35: Flycraft range $400-650/hr.
A36: Fixed operating costs (per owned aircraft, per year)
A37: Captains per aircraft | B37: # | C37: 2 | D37: 2 | E37: 2 | F37: =CHOOSE($C$3,C37,D37,E37) -> 2 | G37: Chief pilot (Henry's partner) is one of the captains.
A38: First officers per aircraft | B38: # | C38: 1 | D38: 1 | E38: 1 | F38: =CHOOSE($C$3,C38,D38,E38) -> 1 | G38: Plus contract pilots for peaks.
A39: Captain salary | B39: $ | C39: 190000 | D39: 175000 | E39: 165000 | F39: =CHOOSE($C$3,C39,D39,E39) -> 175000 | G39: Midsize Part 135 market. Estimate.
A40: First officer salary | B40: $ | C40: 125000 | D40: 115000 | E40: 105000 | F40: =CHOOSE($C$3,C40,D40,E40) -> 115000 | G40: Estimate.
A41: Benefits and payroll tax load | B41: % | C41: 0.28 | D41: 0.25 | E41: 0.22 | F41: =CHOOSE($C$3,C41,D41,E41) -> 0.25 | G41: Flycraft used 43% (corporate); charter typically lower.
A42: Contract pilot budget | B42: $ | C42: 90000 | D42: 60000 | E42: 40000 | F42: =CHOOSE($C$3,C42,D42,E42) -> 60000 | G42: Estimate.
A43: Recurrent training per pilot (sim + Part 135) | B43: $ | C43: 40000 | D43: 35000 | E43: 30000 | F43: =CHOOSE($C$3,C43,D43,E43) -> 35000 | G43: Flycraft range $13-20K sim per pilot; Part 135 adds checkrides and travel.
A44: Hangar at home base (KBJC) | B44: $ | C44: 84000 | D44: 66000 | E44: 54000 | F44: =CHOOSE($C$3,C44,D44,E44) -> 66000 | G44: Flycraft range $2,305-5,470/month heated. KBJC has Sheltair; Jet Aviation FBO opening 2028.
A45: Insurance (hull + $100M+ liability, charter use) | B45: $ | C45: 110000 | D45: 85000 | E45: 70000 | F45: =CHOOSE($C$3,C45,D45,E45) -> 85000 | G45: Flycraft: hull 0.15-0.25% of value + liability; charter use adds premium. Get a broker quote.
A46: Management fee (while on manager's certificate) | B46: $/month | C46: 11000 | D46: 10000 | E46: 8500 | F46: =CHOOSE($C$3,C46,D46,E46) -> 10000 | G46: Light jet ~$3K/month to heavy $10K+ (Jet Linx). Charter-heavy midsize assumed higher.
A47: Manager's commission on charter revenue | B47: % | C47: 0.12 | D47: 0.1 | E47: 0.08 | F47: =CHOOSE($C$3,C47,D47,E47) -> 0.1 | G47: Commonly 10-15% of charter revenue. Negotiate.
A48: Other fixed: CAMP tracking, nav data, Wi-Fi plan, software | B48: $ | C48: 100000 | D48: 80000 | E48: 65000 | F48: =CHOOSE($C$3,C48,D48,E48) -> 80000 | G48: Flycraft range $40-60K corporate; charter adds Wi-Fi and scheduling.
A49: Contingency / unscheduled downtime reserve | B49: $ | C49: 75000 | D49: 50000 | E49: 35000 | F49: =CHOOSE($C$3,C49,D49,E49) -> 50000
A50: Henry's company G&A before own certificate | B50: $ | C50: 110000 | D50: 90000 | E50: 75000 | F50: =CHOOSE($C$3,C50,D50,E50) -> 90000 | G50: Accounting, legal, owner-level insurance, chief pilot management stipend.
A51: Annual cost inflation | B51: % | C51: 0.04 | D51: 0.03 | E51: 0.025 | F51: =CHOOSE($C$3,C51,D51,E51) -> 0.03
A52: Cash reserve to hold (months of fixed cost per aircraft) | B52: months | C52: 6 | D52: 6 | E52: 5 | F52: =CHOOSE($C$3,C52,D52,E52) -> 6 | G52: Lenders and management companies usually require an operating reserve.
A53: Growth: own Part 135 certificate and third-party management
A54: First year operating on own Part 135 certificate | B54: year | C54: 2037 | D54: 2030 | E54: 2029 | F54: =CHOOSE($C$3,C54,D54,E54) -> 2030 | G54: FAA certification typically 12-24 months after application. Downside 2037 = stays on the management company certificate for the whole plan.
A55: Certificate startup cost (year before) | B55: $ | C55: 450000 | D55: 350000 | E55: 275000 | F55: =CHOOSE($C$3,C55,D55,E55) -> 350000 | G55: Required staff hired early (Director of Ops, Chief Pilot, Director of Maintenance), manuals, consultants, proving runs.
A56: Own-certificate overhead (fixed) | B56: $/yr | C56: 1000000 | D56: 850000 | E56: 750000 | F56: =CHOOSE($C$3,C56,D56,E56) -> 850000 | G56: DO, DOM, ops control/dispatch, SMS, ARGUS/Wyvern audits, sales, accounting.
A57: Own-certificate overhead per aircraft operated | B57: $/yr | C57: 60000 | D57: 50000 | E57: 40000 | F57: =CHOOSE($C$3,C57,D57,E57) -> 50000
A58: Net margin per third-party managed aircraft | B58: $/yr | C58: 150000 | D58: 200000 | E58: 225000 | F58: =CHOOSE($C$3,C58,D58,E58) -> 200000 | G58: Management fee + charter commission minus direct staff cost. Estimate.
A59: Exit and tax
A60: Exit year | B60: year | C60: 2036 | D60: 2036 | E60: 2036 | F60: =CHOOSE($C$3,C60,D60,E60) -> 2036 | G60: Henry: grow the fleet over 5-10 years, then exit. 2027-2036 horizon.
A61: EBITDA multiple on management/charter platform | B61: x | C61: 5 | D61: 6 | E61: 6.5 | F61: =CHOOSE($C$3,C61,D61,E61) -> 6 | G61: Applied to third-party management margin only; owned fleet valued at market. Estimate.
A62: Fleet selling costs at exit | B62: % | C62: 0.03 | D62: 0.02 | E62: 0.02 | F62: =CHOOSE($C$3,C62,D62,E62) -> 0.02 | G62: Broker commissions, pre-sale inspections.
A63: Annual decline in aircraft market value | B63: % | C63: 0.07 | D63: 0.05 | E63: 0.035 | F63: =CHOOSE($C$3,C63,D63,E63) -> 0.05 | G63: Estimate; midsize values were firm 2021-2025.
A64: Owner's marginal tax rate (illustrative) | B64: % | C64: 0.37 | D64: 0.37 | E64: 0.37 | F64: =CHOOSE($C$3,C64,D64,E64) -> 0.37 | G64: Memo only. Consult a CPA on material participation and passive loss limits.
A65: First-year bonus depreciation | B65: % | C65: 1 | D65: 1 | E65: 1 | F65: =CHOOSE($C$3,C65,D65,E65) -> 1 | G65: 2025 law restored 100% bonus depreciation permanently; used aircraft qualify; >50% qualified business use. globalair.com

Sheet Startup Budget
A1: Startup budget: first aircraft (Live scenario)
A2: Uses and sources of cash to get Jet #1 flying revenue trips.
A4: Uses of cash | C4: Amount | D4: Note
A5: Purchase price | C5: =Assumptions!$F$7 -> 13500000 | D5: Assumptions
A6: Pre-buy inspection | C6: =Assumptions!$F$9 -> 75000
A7: Closing legal, escrow, title, registration | C7: =Assumptions!$F$10 -> 50000
A8: Part 135 onboarding, conformity, Wi-Fi/avionics | C8: =Assumptions!$F$11 -> 150000
A9: Interior/paint refresh | C9: =Assumptions!$F$12 -> 250000
A10: Initial crew training and hiring | C10: =Assumptions!$F$13 -> 75000
A11: Company formation, legal, accounting, insurance setup | C11: =Assumptions!$F$14 -> 50000
A12: Cash reserve (operating) | C12: ='Unit Economics'!$F$38 -> 618625 | D12: Months of fixed cost per Assumptions
A13: Total uses | C13: =SUM(C5:C12) -> 14768625
A15: Sources of cash | C15: Amount | D15: Note
A16: Aircraft loan | C16: =Assumptions!$F$7*Assumptions!$F$16 -> 10800000 | D16: Senior secured loan at Live LTV
A17: Owner equity (Henry + partners) | C17: =C13-C16 -> 3968625
A18: Total sources | C18: =C16+C17 -> 14768625
A20: Equity as % of total uses | C20: =C17/C13 -> 0.26872001
A22: First full year operating budget (2028) | C22: Amount | D22: Note
A23: Charter revenue | C23: =Forecast!D20+Forecast!D21 -> 4310550 | D23: From Forecast, 2028 column
A24: Variable flight costs | C24: =-Forecast!D26 -> -2260674.9
A25: Crew | C25: =-Forecast!D27 -> -660487.5
A26: Training | C26: =-Forecast!D28 -> -108150
A27: Hangar, insurance, other fixed | C27: =-Forecast!D29 -> -289430
A28: Management fees | C28: =-Forecast!D30 -> -123600
A29: Manager's commission | C29: =-Forecast!D31 -> -431055
A30: Company G&A | C30: =-Forecast!D32 -> -92700
A31: EBITDA | C31: =Forecast!D36 -> 344452.6
A32: Debt service | C32: =-(Forecast!D39+Forecast!D40) -> -1204574.2
A33: Cash flow after debt service | C33: =Forecast!D41 -> -860121.63

Sheet Forecast
A1: 10-year forecast: company P&L, cash flow and equity (Live scenario)
A2: Annual, nominal dollars. Owned jets fly on the management company's certificate until the own-certificate year.
A3: ="Scenario: "&Assumptions!$D$3 -> Scenario: Base
A4: Line item | C4: 2027 | D4: 2028 | E4: 2029 | F4: 2030 | G4: 2031 | H4: 2032 | I4: 2033 | J4: 2034 | K4: 2035 | L4: 2036
A5: Year | C5: 2027 | D5: 2028 | E5: 2029 | F5: 2030 | G5: 2031 | H5: 2032 | I5: 2033 | J5: 2034 | K5: 2035 | L5: 2036
A6: Years from 2027 | C6: =C5-2027 -> 0 | D6: =D5-2027 -> 1 | E6: =E5-2027 -> 2 | F6: =F5-2027 -> 3 | G6: =G5-2027 -> 4 | H6: =H5-2027 -> 5 | I6: =I5-2027 -> 6 | J6: =J5-2027 -> 7 | ... L6: =L5-2027 -> 9
A7: On management company certificate? (1 = yes) | C7: =IF(C5<Assumptions!$F$54,1,0) -> 1 | D7: =IF(D5<Assumptions!$F$54,1,0) -> 1 | E7: =IF(E5<Assumptions!$F$54,1,0) -> 1 | F7: =IF(F5<Assumptions!$F$54,1,0) -> 0 | G7: =IF(G5<Assumptions!$F$54,1,0) -> 0 | H7: =IF(H5<Assumptions!$F$54,1,0) -> 0 | I7: =IF(I5<Assumptions!$F$54,1,0) -> 0 | J7: =IF(J5<Assumptions!$F$54,1,0) -> 0 | ... L7: =IF(L5<Assumptions!$F$54,1,0) -> 0
A8: Cost inflation index | C8: =(1+Assumptions!$F$51)^C6 -> 1 | D8: =(1+Assumptions!$F$51)^D6 -> 1.03 | E8: =(1+Assumptions!$F$51)^E6 -> 1.0609 | F8: =(1+Assumptions!$F$51)^F6 -> 1.092727 | G8: =(1+Assumptions!$F$51)^G6 -> 1.1255088 | H8: =(1+Assumptions!$F$51)^H6 -> 1.1592741 | I8: =(1+Assumptions!$F$51)^I6 -> 1.1940523 | J8: =(1+Assumptions!$F$51)^J6 -> 1.2298739 | ... L8: =(1+Assumptions!$F$51)^L6 -> 1.3047732
A10: Fleet and activity
A11: Owned aircraft (year end) | C11: ='Fleet Plan'!C9 -> 1 | D11: ='Fleet Plan'!D9 -> 1 | E11: ='Fleet Plan'!E9 -> 1 | F11: ='Fleet Plan'!F9 -> 2 | G11: ='Fleet Plan'!G9 -> 2 | H11: ='Fleet Plan'!H9 -> 2 | I11: ='Fleet Plan'!I9 -> 3 | J11: ='Fleet Plan'!J9 -> 3 | ... L11: ='Fleet Plan'!L9 -> 3
A12: Owned aircraft-years in service | C12: =C11*Assumptions!$F$21/12 -> 0.5 | D12: =(C11+D11)/2 -> 1 | E12: =(D11+E11)/2 -> 1 | F12: =(E11+F11)/2 -> 1.5 | G12: =(F11+G11)/2 -> 2 | H12: =(G11+H11)/2 -> 2 | I12: =(H11+I11)/2 -> 2.5 | J12: =(I11+J11)/2 -> 3 | K12: =(J11+K11)/2 -> 3 | L12: =(K11+L11)/2 -> 3
A13: Utilization factor | C13: =IF(C6=0,Assumptions!$F$22,IF(C6=1,Assumptions!$F$23,1)) -> 0.6 | D13: =IF(D6=0,Assumptions!$F$22,IF(D6=1,Assumptions!$F$23,1)) -> 0.9 | E13: =IF(E6=0,Assumptions!$F$22,IF(E6=1,Assumptions!$F$23,1)) -> 1 | F13: =IF(F6=0,Assumptions!$F$22,IF(F6=1,Assumptions!$F$23,1)) -> 1 | G13: =IF(G6=0,Assumptions!$F$22,IF(G6=1,Assumptions!$F$23,1)) -> 1 | H13: =IF(H6=0,Assumptions!$F$22,IF(H6=1,Assumptions!$F$23,1)) -> 1 | I13: =IF(I6=0,Assumptions!$F$22,IF(I6=1,Assumptions!$F$23,1)) -> 1 | J13: =IF(J6=0,Assumptions!$F$22,IF(J6=1,Assumptions!$F$23,1)) -> 1 | ... L13: =IF(L6=0,Assumptions!$F$22,IF(L6=1,Assumptions!$F$23,1)) -> 1
A14: Billable hours | C14: =C12*Assumptions!$F$20*C13 -> 180 | D14: =D12*Assumptions!$F$20*D13 -> 540 | E14: =E12*Assumptions!$F$20*E13 -> 600 | F14: =F12*Assumptions!$F$20*F13 -> 900 | G14: =G12*Assumptions!$F$20*G13 -> 1200 | H14: =H12*Assumptions!$F$20*H13 -> 1200 | I14: =I12*Assumptions!$F$20*I13 -> 1500 | J14: =J12*Assumptions!$F$20*J13 -> 1800 | ... L14: =L12*Assumptions!$F$20*L13 -> 1800
A15: Flight hours incl. positioning | C15: =C14*(1+Assumptions!$F$28) -> 198 | D15: =D14*(1+Assumptions!$F$28) -> 594 | E15: =E14*(1+Assumptions!$F$28) -> 660 | F15: =F14*(1+Assumptions!$F$28) -> 990 | G15: =G14*(1+Assumptions!$F$28) -> 1320 | H15: =H14*(1+Assumptions!$F$28) -> 1320 | I15: =I14*(1+Assumptions!$F$28) -> 1650 | J15: =J14*(1+Assumptions!$F$28) -> 1980 | ... L15: =L14*(1+Assumptions!$F$28) -> 1980
A16: Third-party managed aircraft (year end) | C16: ='Fleet Plan'!C15*(1-C7) -> 0 | D16: ='Fleet Plan'!D15*(1-D7) -> 0 | E16: ='Fleet Plan'!E15*(1-E7) -> 0 | F16: ='Fleet Plan'!F15*(1-F7) -> 1 | G16: ='Fleet Plan'!G15*(1-G7) -> 3 | H16: ='Fleet Plan'!H15*(1-H7) -> 5 | I16: ='Fleet Plan'!I15*(1-I7) -> 7 | J16: ='Fleet Plan'!J15*(1-J7) -> 9 | ... L16: ='Fleet Plan'!L15*(1-L7) -> 12
A17: Third-party managed aircraft (average) | C17: =0 -> 0 | D17: =(C16+D16)/2 -> 0 | E17: =(D16+E16)/2 -> 0 | F17: =(E16+F16)/2 -> 0.5 | G17: =(F16+G16)/2 -> 2 | H17: =(G16+H16)/2 -> 4 | I17: =(H16+I16)/2 -> 6 | J17: =(I16+J16)/2 -> 8 | K17: =(J16+K16)/2 -> 10 | L17: =(K16+L16)/2 -> 11.5
A19: Revenue
A20: Overflow / subcontract revenue | C20: =C14*Assumptions!$F$24*Assumptions!$F$25*(1+Assumptions!$F$27)^C6 -> 630000 | D20: =D14*Assumptions!$F$24*Assumptions!$F$25*(1+Assumptions!$F$27)^D6 -> 1946700 | E20: =E14*Assumptions!$F$24*Assumptions!$F$25*(1+Assumptions!$F$27)^E6 -> 2227890 | F20: =F14*Assumptions!$F$24*Assumptions!$F$25*(1+Assumptions!$F$27)^F6 -> 3442090 | G20: =G14*Assumptions!$F$24*Assumptions!$F$25*(1+Assumptions!$F$27)^G6 -> 4727137 | H20: =H14*Assumptions!$F$24*Assumptions!$F$25*(1+Assumptions!$F$27)^H6 -> 4868951.1 | I20: =I14*Assumptions!$F$24*Assumptions!$F$25*(1+Assumptions!$F$27)^I6 -> 6268774.6 | J20: =J14*Assumptions!$F$24*Assumptions!$F$25*(1+Assumptions!$F$27)^J6 -> 7748205.4 | ... L20: =L14*Assumptions!$F$24*Assumptions!$F$25*(1+Assumptions!$F$27)^L6 -> 8220071.1
A21: Broker / retail charter revenue | C21: =C14*(1-Assumptions!$F$24)*Assumptions!$F$26*(1+Assumptions!$F$27)^C6 -> 765000 | D21: =D14*(1-Assumptions!$F$24)*Assumptions!$F$26*(1+Assumptions!$F$27)^D6 -> 2363850 | E21: =E14*(1-Assumptions!$F$24)*Assumptions!$F$26*(1+Assumptions!$F$27)^E6 -> 2705295 | F21: =F14*(1-Assumptions!$F$24)*Assumptions!$F$26*(1+Assumptions!$F$27)^F6 -> 4179680.8 | G21: =G14*(1-Assumptions!$F$24)*Assumptions!$F$26*(1+Assumptions!$F$27)^G6 -> 5740094.9 | H21: =H14*(1-Assumptions!$F$24)*Assumptions!$F$26*(1+Assumptions!$F$27)^H6 -> 5912297.8 | I21: =I14*(1-Assumptions!$F$24)*Assumptions!$F$26*(1+Assumptions!$F$27)^I6 -> 7612083.4 | J21: =J14*(1-Assumptions!$F$24)*Assumptions!$F$26*(1+Assumptions!$F$27)^J6 -> 9408535.1 | ... L21: =L14*(1-Assumptions!$F$24)*Assumptions!$F$26*(1+Assumptions!$F$27)^L6 -> 9981514.9
A22: Third-party management margin (own certificate) | C22: =C17*Assumptions!$F$58*C8 -> 0 | D22: =D17*Assumptions!$F$58*D8 -> 0 | E22: =E17*Assumptions!$F$58*E8 -> 0 | F22: =F17*Assumptions!$F$58*F8 -> 109272.7 | G22: =G17*Assumptions!$F$58*G8 -> 450203.52 | H22: =H17*Assumptions!$F$58*H8 -> 927419.26 | I22: =I17*Assumptions!$F$58*I8 -> 1432862.8 | J22: =J17*Assumptions!$F$58*J8 -> 1967798.2 | ... L22: =L17*Assumptions!$F$58*L8 -> 3000978.3
A23: Total revenue | C23: =SUM(C20:C22) -> 1395000 | D23: =SUM(D20:D22) -> 4310550 | E23: =SUM(E20:E22) -> 4933185 | F23: =SUM(F20:F22) -> 7731043.5 | G23: =SUM(G20:G22) -> 10917435 | H23: =SUM(H20:H22) -> 11708668 | I23: =SUM(I20:I22) -> 15313721 | J23: =SUM(J20:J22) -> 19124539 | ... L23: =SUM(L20:L22) -> 21202564
A25: Operating costs
A26: Variable flight costs (fuel, maintenance, engines, APU, trip) | C26: =C15*(Assumptions!$F$30*Assumptions!$F$31+Assumptions!$F$32+Assumptions!$F$33+Assumptions!$F$34+Assumptions!$F$35)*C8 -> 731610 | D26: =D15*(Assumptions!$F$30*Assumptions!$F$31+Assumptions!$F$32+Assumptions!$F$33+Assumptions!$F$34+Assumptions!$F$35)*D8 -> 2260674.9 | E26: =E15*(Assumptions!$F$30*Assumptions!$F$31+Assumptions!$F$32+Assumptions!$F$33+Assumptions!$F$34+Assumptions!$F$35)*E8 -> 2587216.8 | F26: =F15*(Assumptions!$F$30*Assumptions!$F$31+Assumptions!$F$32+Assumptions!$F$33+Assumptions!$F$34+Assumptions!$F$35)*F8 -> 3997250 | G26: =G15*(Assumptions!$F$30*Assumptions!$F$31+Assumptions!$F$32+Assumptions!$F$33+Assumptions!$F$34+Assumptions!$F$35)*G8 -> 5489556.7 | H26: =H15*(Assumptions!$F$30*Assumptions!$F$31+Assumptions!$F$32+Assumptions!$F$33+Assumptions!$F$34+Assumptions!$F$35)*H8 -> 5654243.4 | I26: =I15*(Assumptions!$F$30*Assumptions!$F$31+Assumptions!$F$32+Assumptions!$F$33+Assumptions!$F$34+Assumptions!$F$35)*I8 -> 7279838.3 | J26: =J15*(Assumptions!$F$30*Assumptions!$F$31+Assumptions!$F$32+Assumptions!$F$33+Assumptions!$F$34+Assumptions!$F$35)*J8 -> 8997880.2 | ... L26: =L15*(Assumptions!$F$30*Assumptions!$F$31+Assumptions!$F$32+Assumptions!$F$33+Assumptions!$F$34+Assumptions!$F$35)*L8 -> 9545851.1
A27: Crew salaries, benefits, contract pilots | C27: =C12*((Assumptions!$F$37*Assumptions!$F$39+Assumptions!$F$38*Assumptions!$F$40)*(1+Assumptions!$F$41)+Assumptions!$F$42)*C8 -> 320625 | D27: =D12*((Assumptions!$F$37*Assumptions!$F$39+Assumptions!$F$38*Assumptions!$F$40)*(1+Assumptions!$F$41)+Assumptions!$F$42)*D8 -> 660487.5 | E27: =E12*((Assumptions!$F$37*Assumptions!$F$39+Assumptions!$F$38*Assumptions!$F$40)*(1+Assumptions!$F$41)+Assumptions!$F$42)*E8 -> 680302.12 | F27: =F12*((Assumptions!$F$37*Assumptions!$F$39+Assumptions!$F$38*Assumptions!$F$40)*(1+Assumptions!$F$41)+Assumptions!$F$42)*F8 -> 1051066.8 | G27: =G12*((Assumptions!$F$37*Assumptions!$F$39+Assumptions!$F$38*Assumptions!$F$40)*(1+Assumptions!$F$41)+Assumptions!$F$42)*G8 -> 1443465 | H27: =H12*((Assumptions!$F$37*Assumptions!$F$39+Assumptions!$F$38*Assumptions!$F$40)*(1+Assumptions!$F$41)+Assumptions!$F$42)*H8 -> 1486769 | I27: =I12*((Assumptions!$F$37*Assumptions!$F$39+Assumptions!$F$38*Assumptions!$F$40)*(1+Assumptions!$F$41)+Assumptions!$F$42)*I8 -> 1914215.1 | J27: =J12*((Assumptions!$F$37*Assumptions!$F$39+Assumptions!$F$38*Assumptions!$F$40)*(1+Assumptions!$F$41)+Assumptions!$F$42)*J8 -> 2365969.8 | ... L27: =L12*((Assumptions!$F$37*Assumptions!$F$39+Assumptions!$F$38*Assumptions!$F$40)*(1+Assumptions!$F$41)+Assumptions!$F$42)*L8 -> 2510057.4
A28: Recurrent training | C28: =C12*(Assumptions!$F$37+Assumptions!$F$38)*Assumptions!$F$43*C8 -> 52500 | D28: =D12*(Assumptions!$F$37+Assumptions!$F$38)*Assumptions!$F$43*D8 -> 108150 | E28: =E12*(Assumptions!$F$37+Assumptions!$F$38)*Assumptions!$F$43*E8 -> 111394.5 | F28: =F12*(Assumptions!$F$37+Assumptions!$F$38)*Assumptions!$F$43*F8 -> 172104.5 | G28: =G12*(Assumptions!$F$37+Assumptions!$F$38)*Assumptions!$F$43*G8 -> 236356.85 | H28: =H12*(Assumptions!$F$37+Assumptions!$F$38)*Assumptions!$F$43*H8 -> 243447.56 | I28: =I12*(Assumptions!$F$37+Assumptions!$F$38)*Assumptions!$F$43*I8 -> 313438.73 | J28: =J12*(Assumptions!$F$37+Assumptions!$F$38)*Assumptions!$F$43*J8 -> 387410.27 | ... L28: =L12*(Assumptions!$F$37+Assumptions!$F$38)*Assumptions!$F$43*L8 -> 411003.55
A29: Hangar, insurance, other fixed, contingency | C29: =C12*(Assumptions!$F$44+Assumptions!$F$45+Assumptions!$F$48+Assumptions!$F$49)*C8 -> 140500 | D29: =D12*(Assumptions!$F$44+Assumptions!$F$45+Assumptions!$F$48+Assumptions!$F$49)*D8 -> 289430 | E29: =E12*(Assumptions!$F$44+Assumptions!$F$45+Assumptions!$F$48+Assumptions!$F$49)*E8 -> 298112.9 | F29: =F12*(Assumptions!$F$44+Assumptions!$F$45+Assumptions!$F$48+Assumptions!$F$49)*F8 -> 460584.43 | G29: =G12*(Assumptions!$F$44+Assumptions!$F$45+Assumptions!$F$48+Assumptions!$F$49)*G8 -> 632535.95 | H29: =H12*(Assumptions!$F$44+Assumptions!$F$45+Assumptions!$F$48+Assumptions!$F$49)*H8 -> 651512.03 | I29: =I12*(Assumptions!$F$44+Assumptions!$F$45+Assumptions!$F$48+Assumptions!$F$49)*I8 -> 838821.74 | J29: =J12*(Assumptions!$F$44+Assumptions!$F$45+Assumptions!$F$48+Assumptions!$F$49)*J8 -> 1036783.7 | ... L29: =L12*(Assumptions!$F$44+Assumptions!$F$45+Assumptions!$F$48+Assumptions!$F$49)*L8 -> 1099923.8
A30: Management fees (on manager's certificate) | C30: =C7*C12*Assumptions!$F$46*12*C8 -> 60000 | D30: =D7*D12*Assumptions!$F$46*12*D8 -> 123600 | E30: =E7*E12*Assumptions!$F$46*12*E8 -> 127308 | F30: =F7*F12*Assumptions!$F$46*12*F8 -> 0 | G30: =G7*G12*Assumptions!$F$46*12*G8 -> 0 | H30: =H7*H12*Assumptions!$F$46*12*H8 -> 0 | I30: =I7*I12*Assumptions!$F$46*12*I8 -> 0 | J30: =J7*J12*Assumptions!$F$46*12*J8 -> 0 | ... L30: =L7*L12*Assumptions!$F$46*12*L8 -> 0
A31: Manager's charter commission | C31: =C7*(C20+C21)*Assumptions!$F$47 -> 139500 | D31: =D7*(D20+D21)*Assumptions!$F$47 -> 431055 | E31: =E7*(E20+E21)*Assumptions!$F$47 -> 493318.5 | F31: =F7*(F20+F21)*Assumptions!$F$47 -> 0 | G31: =G7*(G20+G21)*Assumptions!$F$47 -> 0 | H31: =H7*(H20+H21)*Assumptions!$F$47 -> 0 | I31: =I7*(I20+I21)*Assumptions!$F$47 -> 0 | J31: =J7*(J20+J21)*Assumptions!$F$47 -> 0 | ... L31: =L7*(L20+L21)*Assumptions!$F$47 -> 0
A32: Company G&A (before own certificate) | C32: =C7*Assumptions!$F$50*C8 -> 90000 | D32: =D7*Assumptions!$F$50*D8 -> 92700 | E32: =E7*Assumptions!$F$50*E8 -> 95481 | F32: =F7*Assumptions!$F$50*F8 -> 0 | G32: =G7*Assumptions!$F$50*G8 -> 0 | H32: =H7*Assumptions!$F$50*H8 -> 0 | I32: =I7*Assumptions!$F$50*I8 -> 0 | J32: =J7*Assumptions!$F$50*J8 -> 0 | ... L32: =L7*Assumptions!$F$50*L8 -> 0
A33: Own-certificate overhead | C33: =(1-C7)*(Assumptions!$F$56+Assumptions!$F$57*(C12+C17))*C8 -> 0 | D33: =(1-D7)*(Assumptions!$F$56+Assumptions!$F$57*(D12+D17))*D8 -> 0 | E33: =(1-E7)*(Assumptions!$F$56+Assumptions!$F$57*(E12+E17))*E8 -> 0 | F33: =(1-F7)*(Assumptions!$F$56+Assumptions!$F$57*(F12+F17))*F8 -> 1038090.7 | G33: =(1-G7)*(Assumptions!$F$56+Assumptions!$F$57*(G12+G17))*G8 -> 1181784.3 | H33: =(1-H7)*(Assumptions!$F$56+Assumptions!$F$57*(H12+H17))*H8 -> 1333165.2 | I33: =(1-I7)*(Assumptions!$F$56+Assumptions!$F$57*(I12+I17))*I8 -> 1522416.7 | J33: =(1-J7)*(Assumptions!$F$56+Assumptions!$F$57*(J12+J17))*J8 -> 1721823.4 | ... L33: =(1-L7)*(Assumptions!$F$56+Assumptions!$F$57*(L12+L17))*L8 -> 2055017.8
A34: Total operating costs | C34: =SUM(C26:C33) -> 1534735 | D34: =SUM(D26:D33) -> 3966097.4 | E34: =SUM(E26:E33) -> 4393133.9 | F34: =SUM(F26:F33) -> 6719096.4 | G34: =SUM(G26:G33) -> 8983698.8 | H34: =SUM(H26:H33) -> 9369137.1 | I34: =SUM(I26:I33) -> 11868731 | J34: =SUM(J26:J33) -> 14509867 | ... L34: =SUM(L26:L33) -> 15621854
A36: EBITDA | C36: =C23-C34 -> -139735 | D36: =D23-D34 -> 344452.6 | E36: =E23-E34 -> 540051.15 | F36: =F23-F34 -> 1011947.2 | G36: =G23-G34 -> 1933736.7 | H36: =H23-H34 -> 2339531 | I36: =I23-I34 -> 3444990.1 | J36: =J23-J34 -> 4614671.2 | ... L36: =L23-L34 -> 5580710.6
A37: EBITDA margin | C37: =IF(C23=0,0,C36/C23) -> -0.10016846 | D37: =IF(D23=0,0,D36/D23) -> 0.0799092 | E37: =IF(E23=0,0,E36/E23) -> 0.10947312 | F37: =IF(F23=0,0,F36/F23) -> 0.13089399 | G37: =IF(G23=0,0,G36/G23) -> 0.17712371 | H37: =IF(H23=0,0,H36/H23) -> 0.19981188 | I37: =IF(I23=0,0,I36/I23) -> 0.22496101 | J37: =IF(J23=0,0,J36/J23) -> 0.24129582 | ... L37: =IF(L23=0,0,L36/L23) -> 0.26320923
A38: One-time: own-certificate startup | C38: =IF(C5=Assumptions!$F$54-1,Assumptions!$F$55,0) -> 0 | D38: =IF(D5=Assumptions!$F$54-1,Assumptions!$F$55,0) -> 0 | E38: =IF(E5=Assumptions!$F$54-1,Assumptions!$F$55,0) -> 350000 | F38: =IF(F5=Assumptions!$F$54-1,Assumptions!$F$55,0) -> 0 | G38: =IF(G5=Assumptions!$F$54-1,Assumptions!$F$55,0) -> 0 | H38: =IF(H5=Assumptions!$F$54-1,Assumptions!$F$55,0) -> 0 | I38: =IF(I5=Assumptions!$F$54-1,Assumptions!$F$55,0) -> 0 | J38: =IF(J5=Assumptions!$F$54-1,Assumptions!$F$55,0) -> 0 | ... L38: =IF(L5=Assumptions!$F$54-1,Assumptions!$F$55,0) -> 0
A39: Interest | C39: ='Debt Schedule'!C92 -> 783000 | D39: ='Debt Schedule'!D92 -> 752435.87 | E39: ='Debt Schedule'!E92 -> 719655.84 | F39: ='Debt Schedule'!F92 -> 1467499.3 | G39: ='Debt Schedule'!G92 -> 1399229.7 | H39: ='Debt Schedule'!H92 -> 1326010.6 | I39: ='Debt Schedule'!I92 -> 2030483.1 | J39: ='Debt Schedule'!J92 -> 1915698.2 | ... L39: ='Debt Schedule'!L92 -> 1660559.4
A40: Principal repayment | C40: ='Debt Schedule'!C93 -> 421574.23 | D40: ='Debt Schedule'!D93 -> 452138.36 | E40: ='Debt Schedule'!E93 -> 484918.39 | F40: ='Debt Schedule'!F93 -> 941649.2 | G40: ='Debt Schedule'!G93 -> 1009918.8 | H40: ='Debt Schedule'!H93 -> 1083137.9 | I40: ='Debt Schedule'!I93 -> 1583239.6 | J40: ='Debt Schedule'!J93 -> 1698024.5 | ... L40: ='Debt Schedule'!L93 -> 1953163.3
A41: Cash flow after debt service | C41: =C36-C38-C39-C40 -> -1344309.2 | D41: =D36-D38-D39-D40 -> -860121.63 | E41: =E36-E38-E39-E40 -> -1014523.1 | F41: =F36-F38-F39-F40 -> -1397201.3 | G41: =G36-G38-G39-G40 -> -475411.77 | H41: =H36-H38-H39-H40 -> -69617.449 | I41: =I36-I38-I39-I40 -> -168732.56 | J41: =J36-J38-J39-J40 -> 1000948.5 | ... L41: =L36-L38-L39-L40 -> 1966987.9
A43: Aircraft purchases and owner equity
A44: Aircraft purchased | C44: =C11 -> 1 | D44: =D11-C11 -> 0 | E44: =E11-D11 -> 0 | F44: =F11-E11 -> 1 | G44: =G11-F11 -> 0 | H44: =H11-G11 -> 0 | I44: =I11-H11 -> 1 | J44: =J11-I11 -> 0 | K44: =K11-J11 -> 0 | L44: =L11-K11 -> 0
A45: Price per aircraft | C45: =Assumptions!$F$7*(1+Assumptions!$F$8)^C6 -> 13500000 | D45: =Assumptions!$F$7*(1+Assumptions!$F$8)^D6 -> 13500000 | E45: =Assumptions!$F$7*(1+Assumptions!$F$8)^E6 -> 13500000 | F45: =Assumptions!$F$7*(1+Assumptions!$F$8)^F6 -> 13500000 | G45: =Assumptions!$F$7*(1+Assumptions!$F$8)^G6 -> 13500000 | H45: =Assumptions!$F$7*(1+Assumptions!$F$8)^H6 -> 13500000 | I45: =Assumptions!$F$7*(1+Assumptions!$F$8)^I6 -> 13500000 | J45: =Assumptions!$F$7*(1+Assumptions!$F$8)^J6 -> 13500000 | ... L45: =Assumptions!$F$7*(1+Assumptions!$F$8)^L6 -> 13500000
A46: Aircraft purchases (total price) | C46: =C44*C45 -> 13500000 | D46: =D44*D45 -> 0 | E46: =E44*E45 -> 0 | F46: =F44*F45 -> 13500000 | G46: =G44*G45 -> 0 | H46: =H44*H45 -> 0 | I46: =I44*I45 -> 13500000 | J46: =J44*J45 -> 0 | ... L46: =L44*L45 -> 0
A47: Less: new loans | C47: =-C46*Assumptions!$F$16 -> -10800000 | D47: =-D46*Assumptions!$F$16 -> 0 | E47: =-E46*Assumptions!$F$16 -> 0 | F47: =-F46*Assumptions!$F$16 -> -10800000 | G47: =-G46*Assumptions!$F$16 -> 0 | H47: =-H46*Assumptions!$F$16 -> 0 | I47: =-I46*Assumptions!$F$16 -> -10800000 | J47: =-J46*Assumptions!$F$16 -> 0 | ... L47: =-L46*Assumptions!$F$16 -> 0
A48: Acquisition, onboarding, refurb, training | C48: =C44*(Assumptions!$F$9+Assumptions!$F$10+Assumptions!$F$11+Assumptions!$F$12+Assumptions!$F$13)*C8 -> 600000 | D48: =D44*(Assumptions!$F$9+Assumptions!$F$10+Assumptions!$F$11+Assumptions!$F$12+Assumptions!$F$13)*D8 -> 0 | E48: =E44*(Assumptions!$F$9+Assumptions!$F$10+Assumptions!$F$11+Assumptions!$F$12+Assumptions!$F$13)*E8 -> 0 | F48: =F44*(Assumptions!$F$9+Assumptions!$F$10+Assumptions!$F$11+Assumptions!$F$12+Assumptions!$F$13)*F8 -> 655636.2 | G48: =G44*(Assumptions!$F$9+Assumptions!$F$10+Assumptions!$F$11+Assumptions!$F$12+Assumptions!$F$13)*G8 -> 0 | H48: =H44*(Assumptions!$F$9+Assumptions!$F$10+Assumptions!$F$11+Assumptions!$F$12+Assumptions!$F$13)*H8 -> 0 | I48: =I44*(Assumptions!$F$9+Assumptions!$F$10+Assumptions!$F$11+Assumptions!$F$12+Assumptions!$F$13)*I8 -> 716431.38 | J48: =J44*(Assumptions!$F$9+Assumptions!$F$10+Assumptions!$F$11+Assumptions!$F$12+Assumptions!$F$13)*J8 -> 0 | ... L48: =L44*(Assumptions!$F$9+Assumptions!$F$10+Assumptions!$F$11+Assumptions!$F$12+Assumptions!$F$13)*L8 -> 0
A49: Company setup | C49: =Assumptions!$F$14 -> 50000 | D49: =0 -> 0 | E49: =0 -> 0 | F49: =0 -> 0 | G49: =0 -> 0 | H49: =0 -> 0 | I49: =0 -> 0 | J49: =0 -> 0 | K49: =0 -> 0 | L49: =0 -> 0
A50: Equity needed for purchases | C50: =SUM(C46:C49) -> 3350000 | D50: =SUM(D46:D49) -> 0 | E50: =SUM(E46:E49) -> 0 | F50: =SUM(F46:F49) -> 3355636.2 | G50: =SUM(G46:G49) -> 0 | H50: =SUM(H46:H49) -> 0 | I50: =SUM(I46:I49) -> 3416431.4 | J50: =SUM(J46:J49) -> 0 | ... L50: =SUM(L46:L49) -> 0
A52: Beginning cash | C52: =0 -> 0 | D52: =C55 -> 618625 | E52: =D55 -> 637183.75 | F52: =E55 -> 656299.26 | G52: =F55 -> 1351976.5 | H52: =G55 -> 1392535.8 | I52: =H55 -> 1434311.8 | J52: =I55 -> 2216011.8 | K52: =J55 -> 3216960.3 | L52: =K55 -> 4736380
A53: Minimum cash reserve | C53: =C11*'Unit Economics'!$F$38*C8 -> 618625 | D53: =D11*'Unit Economics'!$F$38*D8 -> 637183.75 | E53: =E11*'Unit Economics'!$F$38*E8 -> 656299.26 | F53: =F11*'Unit Economics'!$F$38*F8 -> 1351976.5 | G53: =G11*'Unit Economics'!$F$38*G8 -> 1392535.8 | H53: =H11*'Unit Economics'!$F$38*H8 -> 1434311.8 | I53: =I11*'Unit Economics'!$F$38*I8 -> 2216011.8 | J53: =J11*'Unit Economics'!$F$38*J8 -> 2282492.2 | ... L53: =L11*'Unit Economics'!$F$38*L8 -> 2421495.9
A54: Owner equity contributed | C54: =MAX(0,C53-(C52+C41-C50)) -> 5312934.2 | D54: =MAX(0,D53-(D52+D41-D50)) -> 878680.38 | E54: =MAX(0,E53-(E52+E41-E50)) -> 1033638.6 | F54: =MAX(0,F53-(F52+F41-F50)) -> 5448514.7 | G54: =MAX(0,G53-(G52+G41-G50)) -> 515971.07 | H54: =MAX(0,H53-(H52+H41-H50)) -> 111393.52 | I54: =MAX(0,I53-(I52+I41-I50)) -> 4366863.9 | J54: =MAX(0,J53-(J52+J41-J50)) -> 0 | ... L54: =MAX(0,L53-(L52+L41-L50)) -> 0
A55: Ending cash | C55: =C52+C41-C50+C54 -> 618625 | D55: =D52+D41-D50+D54 -> 637183.75 | E55: =E52+E41-E50+E54 -> 656299.26 | F55: =F52+F41-F50+F54 -> 1351976.5 | G55: =G52+G41-G50+G54 -> 1392535.8 | H55: =H52+H41-H50+H54 -> 1434311.8 | I55: =I52+I41-I50+I54 -> 2216011.8 | J55: =J52+J41-J50+J54 -> 3216960.3 | ... L55: =L52+L41-L50+L54 -> 6703368
A56: Cumulative owner equity | C56: =C54 -> 5312934.2 | D56: =C56+D54 -> 6191614.6 | E56: =D56+E54 -> 7225253.2 | F56: =E56+F54 -> 12673768 | G56: =F56+G54 -> 13189739 | H56: =G56+H54 -> 13301133 | I56: =H56+I54 -> 17667996 | J56: =I56+J54 -> 17667996 | K56: =J56+K54 -> 17667996 | L56: =K56+L54 -> 17667996
A58: Balance sheet view (year end)
A59: Fleet market value | C59: ='Debt Schedule'!C95 -> 12825000 | D59: ='Debt Schedule'!D95 -> 12183750 | E59: ='Debt Schedule'!E95 -> 11574562 | F59: ='Debt Schedule'!F95 -> 23820834 | G59: ='Debt Schedule'!G95 -> 22629793 | H59: ='Debt Schedule'!H95 -> 21498303 | I59: ='Debt Schedule'!I95 -> 33248388 | J59: ='Debt Schedule'!J95 -> 31585968 | ... L59: ='Debt Schedule'!L95 -> 28506337
A60: Debt outstanding | C60: ='Debt Schedule'!C94 -> 10378426 | D60: ='Debt Schedule'!D94 -> 9926287.4 | E60: ='Debt Schedule'!E94 -> 9441369 | F60: ='Debt Schedule'!F94 -> 19299720 | G60: ='Debt Schedule'!G94 -> 18289801 | H60: ='Debt Schedule'!H94 -> 17206663 | I60: ='Debt Schedule'!I94 -> 26423424 | J60: ='Debt Schedule'!J94 -> 24725399 | ... L60: ='Debt Schedule'!L94 -> 20951105
A61: Net asset value (fleet + cash - debt) | C61: =C59+C55-C60 -> 3065199.2 | D61: =D59+D55-D60 -> 2894646.3 | E61: =E59+E55-E60 -> 2789492.7 | F61: =F59+F55-F60 -> 5873091 | G61: =G59+G55-G60 -> 5732527.4 | H61: =H59+H55-H60 -> 5725951.7 | I61: =I59+I55-I60 -> 9040976.1 | J61: =J59+J55-J60 -> 10077530 | ... L61: =L59+L55-L60 -> 14258600
A62: Loan-to-value on fleet | C62: =IF(C59=0,0,C60/C59) -> 0.80923398 | D62: =IF(D59=0,0,D60/D59) -> 0.81471529 | E62: =IF(E59=0,0,E60/E59) -> 0.81569986 | F62: =IF(F59=0,0,F60/F59) -> 0.81020335 | G62: =IF(G59=0,0,G60/G59) -> 0.80821779 | H62: =IF(H59=0,0,H60/H59) -> 0.80037309 | I62: =IF(I59=0,0,I60/I59) -> 0.79472796 | J62: =IF(J59=0,0,J60/J59) -> 0.78279693 | ... L62: =IF(L59=0,0,L60/L59) -> 0.73496307
A64: Memo: illustrative owner tax effect (not in cash flow; consult a CPA)
A65: Tax depreciation (bonus in purchase year) | C65: =C46*Assumptions!$F$65 -> 13500000 | D65: =D46*Assumptions!$F$65 -> 0 | E65: =E46*Assumptions!$F$65 -> 0 | F65: =F46*Assumptions!$F$65 -> 13500000 | G65: =G46*Assumptions!$F$65 -> 0 | H65: =H46*Assumptions!$F$65 -> 0 | I65: =I46*Assumptions!$F$65 -> 13500000 | J65: =J46*Assumptions!$F$65 -> 0 | ... L65: =L46*Assumptions!$F$65 -> 0
A66: Taxable income (loss) passed to owners | C66: =C36-C38-C39-C65 -> -14422735 | D66: =D36-D38-D39-D65 -> -407983.27 | E66: =E36-E38-E39-E65 -> -529604.69 | F66: =F36-F38-F39-F65 -> -13955552 | G66: =G36-G38-G39-G65 -> 534507 | H66: =H36-H38-H39-H65 -> 1013520.4 | I66: =I36-I38-I39-I65 -> -12085493 | J66: =J36-J38-J39-J65 -> 2698973 | ... L66: =L36-L38-L39-L65 -> 3920151.2
A67: Tax saved (owed) at owner's rate, if losses are usable | C67: =-C66*Assumptions!$F$64 -> 5336412 | D67: =-D66*Assumptions!$F$64 -> 150953.81 | E67: =-E66*Assumptions!$F$64 -> 195953.74 | F67: =-F66*Assumptions!$F$64 -> 5163554.3 | G67: =-G66*Assumptions!$F$64 -> -197767.59 | H67: =-H66*Assumptions!$F$64 -> -375002.56 | I67: =-I66*Assumptions!$F$64 -> 4471632.4 | J67: =-J66*Assumptions!$F$64 -> -998620.02 | ... L67: =-L66*Assumptions!$F$64 -> -1450455.9
A68: Bonus depreciation is recaptured as ordinary income when aircraft are sold at exit. Losses may be limited by passive-activity and at-risk rules unless Henry materially participates.
A70: Equity cash flows for IRR
A71: Exit year flag | C71: =IF(C5=Assumptions!$F$60,1,0) -> 0 | D71: =IF(D5=Assumptions!$F$60,1,0) -> 0 | E71: =IF(E5=Assumptions!$F$60,1,0) -> 0 | F71: =IF(F5=Assumptions!$F$60,1,0) -> 0 | G71: =IF(G5=Assumptions!$F$60,1,0) -> 0 | H71: =IF(H5=Assumptions!$F$60,1,0) -> 0 | I71: =IF(I5=Assumptions!$F$60,1,0) -> 0 | J71: =IF(J5=Assumptions!$F$60,1,0) -> 0 | ... L71: =IF(L5=Assumptions!$F$60,1,0) -> 1
A72: Owner cash flow (contributions negative, exit proceeds positive) | C72: =IF(C5>Assumptions!$F$60,0,-C54+C71*Exit!$C$15) -> -5312934.2 | D72: =IF(D5>Assumptions!$F$60,0,-D54+D71*Exit!$C$15) -> -878680.38 | E72: =IF(E5>Assumptions!$F$60,0,-E54+E71*Exit!$C$15) -> -1033638.6 | F72: =IF(F5>Assumptions!$F$60,0,-F54+F71*Exit!$C$15) -> -5448514.7 | G72: =IF(G5>Assumptions!$F$60,0,-G54+G71*Exit!$C$15) -> -515971.07 | H72: =IF(H5>Assumptions!$F$60,0,-H54+H71*Exit!$C$15) -> -111393.52 | I72: =IF(I5>Assumptions!$F$60,0,-I54+I71*Exit!$C$15) -> -4366863.9 | J72: =IF(J5>Assumptions!$F$60,0,-J54+J71*Exit!$C$15) -> 0 | ... L72: =IF(L5>Assumptions!$F$60,0,-L54+L71*Exit!$C$15) -> 31694343

Sheet Fleet Plan
A1: Fleet plan by scenario
A2: Aircraft counts at year end. Owned = financed Latitudes. Third-party = other owners' jets managed on your certificate (only counts once you hold one).
A4: Item | C4: 2027 | D4: 2028 | E4: 2029 | F4: 2030 | G4: 2031 | H4: 2032 | I4: 2033 | J4: 2034 | K4: 2035 | L4: 2036
A5: Owned aircraft (year end)
A6: Downside | C6: 1 | D6: 1 | E6: 1 | F6: 1 | G6: 1 | H6: 1 | I6: 1 | J6: 1 | K6: 1 | L6: 1
A7: Base | C7: 1 | D7: 1 | E7: 1 | F7: 2 | G7: 2 | H7: 2 | I7: 3 | J7: 3 | K7: 3 | L7: 3
A8: Upside | C8: 1 | D8: 1 | E8: 2 | F8: 2 | G8: 3 | H8: 3 | I8: 4 | J8: 4 | K8: 4 | L8: 4
A9: Live (selected scenario) | C9: =CHOOSE(Assumptions!$C$3,C6,C7,C8) -> 1 | D9: =CHOOSE(Assumptions!$C$3,D6,D7,D8) -> 1 | E9: =CHOOSE(Assumptions!$C$3,E6,E7,E8) -> 1 | F9: =CHOOSE(Assumptions!$C$3,F6,F7,F8) -> 2 | G9: =CHOOSE(Assumptions!$C$3,G6,G7,G8) -> 2 | H9: =CHOOSE(Assumptions!$C$3,H6,H7,H8) -> 2 | I9: =CHOOSE(Assumptions!$C$3,I6,I7,I8) -> 3 | J9: =CHOOSE(Assumptions!$C$3,J6,J7,J8) -> 3 | ... L9: =CHOOSE(Assumptions!$C$3,L6,L7,L8) -> 3
A11: Third-party managed aircraft (year end)
A12: Downside | C12: 0 | D12: 0 | E12: 0 | F12: 0 | G12: 0 | H12: 0 | I12: 0 | J12: 0 | K12: 0 | L12: 0
A13: Base | C13: 0 | D13: 0 | E13: 0 | F13: 1 | G13: 3 | H13: 5 | I13: 7 | J13: 9 | K13: 11 | L13: 12
A14: Upside | C14: 0 | D14: 0 | E14: 1 | F14: 3 | G14: 5 | H14: 7 | I14: 9 | J14: 11 | K14: 12 | L14: 14
A15: Live (selected scenario) | C15: =CHOOSE(Assumptions!$C$3,C12,C13,C14) -> 0 | D15: =CHOOSE(Assumptions!$C$3,D12,D13,D14) -> 0 | E15: =CHOOSE(Assumptions!$C$3,E12,E13,E14) -> 0 | F15: =CHOOSE(Assumptions!$C$3,F12,F13,F14) -> 1 | G15: =CHOOSE(Assumptions!$C$3,G12,G13,G14) -> 3 | H15: =CHOOSE(Assumptions!$C$3,H12,H13,H14) -> 5 | I15: =CHOOSE(Assumptions!$C$3,I12,I13,I14) -> 7 | J15: =CHOOSE(Assumptions!$C$3,J12,J13,J14) -> 9 | ... L15: =CHOOSE(Assumptions!$C$3,L12,L13,L14) -> 12

Sheet Unit Economics
A1: Unit economics: one Latitude, mature year, on management company certificate
A2: Today's dollars, no inflation. Shows whether a single financed jet carries itself.
A4: Line item | C4: Downside | D4: Base | E4: Upside | F4: Live
A5: Billable hours | C5: =Assumptions!$C$20 -> 500 | D5: =Assumptions!$D$20 -> 600 | E5: =Assumptions!$E$20 -> 700 | F5: =Assumptions!$F$20 -> 600
A6: Blended rate per billable hour | C6: =Assumptions!$C$24*Assumptions!$C$25+(1-Assumptions!$C$24)*Assumptions!$C$26 -> 7500 | D6: =Assumptions!$D$24*Assumptions!$D$25+(1-Assumptions!$D$24)*Assumptions!$D$26 -> 7750 | E6: =Assumptions!$E$24*Assumptions!$E$25+(1-Assumptions!$E$24)*Assumptions!$E$26 -> 7950 | F6: =Assumptions!$F$24*Assumptions!$F$25+(1-Assumptions!$F$24)*Assumptions!$F$26 -> 7750
A7: Charter revenue | C7: =C5*C6 -> 3750000 | D7: =D5*D6 -> 4650000 | E7: =E5*E6 -> 5565000 | F7: =F5*F6 -> 4650000
A8: Less manager's commission | C8: =-C7*Assumptions!$C$47 -> -450000 | D8: =-D7*Assumptions!$D$47 -> -465000 | E8: =-E7*Assumptions!$E$47 -> -445200 | F8: =-F7*Assumptions!$F$47 -> -465000
A9: Net charter revenue to owner | C9: =C7+C8 -> 3300000 | D9: =D7+D8 -> 4185000 | E9: =E7+E8 -> 5119800 | F9: =F7+F8 -> 4185000
A11: Flight hours incl. unpaid positioning | C11: =C5*(1+Assumptions!$C$28) -> 575 | D11: =D5*(1+Assumptions!$D$28) -> 660 | E11: =E5*(1+Assumptions!$E$28) -> 756 | F11: =F5*(1+Assumptions!$F$28) -> 660
A12: Variable cost per flight hour | C12: =Assumptions!$C$30*Assumptions!$C$31+Assumptions!$C$32+Assumptions!$C$33+Assumptions!$C$34+Assumptions!$C$35 -> 4145 | D12: =Assumptions!$D$30*Assumptions!$D$31+Assumptions!$D$32+Assumptions!$D$33+Assumptions!$D$34+Assumptions!$D$35 -> 3695 | E12: =Assumptions!$E$30*Assumptions!$E$31+Assumptions!$E$32+Assumptions!$E$33+Assumptions!$E$34+Assumptions!$E$35 -> 3300 | F12: =Assumptions!$F$30*Assumptions!$F$31+Assumptions!$F$32+Assumptions!$F$33+Assumptions!$F$34+Assumptions!$F$35 -> 3695
A13: Variable costs | C13: =-C11*C12 -> -2383375 | D13: =-D11*D12 -> -2438700 | E13: =-E11*E12 -> -2494800 | F13: =-F11*F12 -> -2438700
A15: Crew salaries and benefits | C15: =-((Assumptions!$C$37*Assumptions!$C$39+Assumptions!$C$38*Assumptions!$C$40)*(1+Assumptions!$C$41)+Assumptions!$C$42) -> -736400 | D15: =-((Assumptions!$D$37*Assumptions!$D$39+Assumptions!$D$38*Assumptions!$D$40)*(1+Assumptions!$D$41)+Assumptions!$D$42) -> -641250 | E15: =-((Assumptions!$E$37*Assumptions!$E$39+Assumptions!$E$38*Assumptions!$E$40)*(1+Assumptions!$E$41)+Assumptions!$E$42) -> -570700 | F15: =-((Assumptions!$F$37*Assumptions!$F$39+Assumptions!$F$38*Assumptions!$F$40)*(1+Assumptions!$F$41)+Assumptions!$F$42) -> -641250
A16: Recurrent training | C16: =-(Assumptions!$C$37+Assumptions!$C$38)*Assumptions!$C$43 -> -120000 | D16: =-(Assumptions!$D$37+Assumptions!$D$38)*Assumptions!$D$43 -> -105000 | E16: =-(Assumptions!$E$37+Assumptions!$E$38)*Assumptions!$E$43 -> -90000 | F16: =-(Assumptions!$F$37+Assumptions!$F$38)*Assumptions!$F$43 -> -105000
A17: Hangar | C17: =-Assumptions!$C$44 -> -84000 | D17: =-Assumptions!$D$44 -> -66000 | E17: =-Assumptions!$E$44 -> -54000 | F17: =-Assumptions!$F$44 -> -66000
A18: Insurance | C18: =-Assumptions!$C$45 -> -110000 | D18: =-Assumptions!$D$45 -> -85000 | E18: =-Assumptions!$E$45 -> -70000 | F18: =-Assumptions!$F$45 -> -85000
A19: Management fee | C19: =-Assumptions!$C$46*12 -> -132000 | D19: =-Assumptions!$D$46*12 -> -120000 | E19: =-Assumptions!$E$46*12 -> -102000 | F19: =-Assumptions!$F$46*12 -> -120000
A20: Other fixed | C20: =-Assumptions!$C$48 -> -100000 | D20: =-Assumptions!$D$48 -> -80000 | E20: =-Assumptions!$E$48 -> -65000 | F20: =-Assumptions!$F$48 -> -80000
A21: Contingency | C21: =-Assumptions!$C$49 -> -75000 | D21: =-Assumptions!$D$49 -> -50000 | E21: =-Assumptions!$E$49 -> -35000 | F21: =-Assumptions!$F$49 -> -50000
A22: Company G&A | C22: =-Assumptions!$C$50 -> -110000 | D22: =-Assumptions!$D$50 -> -90000 | E22: =-Assumptions!$E$50 -> -75000 | F22: =-Assumptions!$F$50 -> -90000
A23: Total fixed costs | C23: =SUM(C15:C22) -> -1467400 | D23: =SUM(D15:D22) -> -1237250 | E23: =SUM(E15:E22) -> -1061700 | F23: =SUM(F15:F22) -> -1237250
A25: EBITDA (operating cash flow before debt) | C25: =C9+C13+C23 -> -550775 | D25: =D9+D13+D23 -> 509050 | E25: =E9+E13+E23 -> 1563300 | F25: =F9+F13+F23 -> 509050
A26: EBITDA margin | C26: =IF(C7=0,0,C25/C7) -> -0.14687333 | D26: =IF(D7=0,0,D25/D7) -> 0.10947312 | E26: =IF(E7=0,0,E25/E7) -> 0.28091644 | F26: =IF(F7=0,0,F25/F7) -> 0.10947312
A28: Loan amount | C28: =Assumptions!$C$7*Assumptions!$C$16 -> 12000000 | D28: =Assumptions!$D$7*Assumptions!$D$16 -> 10800000 | E28: =Assumptions!$E$7*Assumptions!$E$16 -> 10000000 | F28: =Assumptions!$F$7*Assumptions!$F$16 -> 10800000
A29: Annual debt service | C29: =-PMT(Assumptions!$C$17,Assumptions!$C$18,-C28) -> -1401954.5 | D29: =-PMT(Assumptions!$D$17,Assumptions!$D$18,-D28) -> -1204574.2 | E29: =-PMT(Assumptions!$E$17,Assumptions!$E$18,-E28) -> -925666.96 | F29: =-PMT(Assumptions!$F$17,Assumptions!$F$18,-F28) -> -1204574.2
A30: Cash flow after debt service | C30: =C25+C29 -> -1952729.5 | D30: =D25+D29 -> -695524.23 | E30: =E25+E29 -> 637633.04 | F30: =F25+F29 -> -695524.23
A31: Of which: first-year interest | C31: =-C28*Assumptions!$C$17 -> -960000 | D31: =-D28*Assumptions!$D$17 -> -783000 | E31: =-E28*Assumptions!$E$17 -> -675000 | F31: =-F28*Assumptions!$F$17 -> -783000
A32: First-year decline in aircraft value | C32: =-Assumptions!$C$7*Assumptions!$C$63 -> -1050000 | D32: =-Assumptions!$D$7*Assumptions!$D$63 -> -675000 | E32: =-Assumptions!$E$7*Assumptions!$E$63 -> -437500 | F32: =-Assumptions!$F$7*Assumptions!$F$63 -> -675000
A33: Economic profit (EBITDA - interest - value decline) | C33: =C25+C31+C32 -> -2560775 | D33: =D25+D31+D32 -> -948950 | E33: =E25+E31+E32 -> 450800 | F33: =F25+F31+F32 -> -948950
A35: Contribution per billable hour | C35: =C6*(1-Assumptions!$C$47)-C12*(1+Assumptions!$C$28) -> 1833.25 | D35: =D6*(1-Assumptions!$D$47)-D12*(1+Assumptions!$D$28) -> 2910.5 | E35: =E6*(1-Assumptions!$E$47)-E12*(1+Assumptions!$E$28) -> 3750 | F35: =F6*(1-Assumptions!$F$47)-F12*(1+Assumptions!$F$28) -> 2910.5
A36: Breakeven billable hours (EBITDA = 0) | C36: =IF(C35<=0,0,-C23/C35) -> 800.43638 | D36: =IF(D35<=0,0,-D23/D35) -> 425.09878 | E36: =IF(E35<=0,0,-E23/E35) -> 283.12 | F36: =IF(F35<=0,0,-F23/F35) -> 425.09878
A37: Breakeven billable hours incl. debt service | C37: =IF(C35<=0,0,-(C23+C29)/C35) -> 1565.1736 | D37: =IF(D35<=0,0,-(D23+D29)/D35) -> 838.9707 | E37: =IF(E35<=0,0,-(E23+E29)/E35) -> 529.96452 | F37: =IF(F35<=0,0,-(F23+F29)/F35) -> 838.9707
A38: Cash reserve to hold | C38: =-C23/12*Assumptions!$C$52 -> 733700 | D38: =-D23/12*Assumptions!$D$52 -> 618625 | E38: =-E23/12*Assumptions!$E$52 -> 442375 | F38: =-F23/12*Assumptions!$F$52 -> 618625
A40: Sensitivity: Live scenario, cash flow after debt service by billable hours
A41: Billable hours | C41: EBITDA | D41: Debt service | E41: Cash after debt | F41: Per-hour margin
A42: 300 | C42: =A42*$F$35+$F$23 -> -364100 | D42: =$F$29 -> -1204574.2 | E42: =C42+D42 -> -1568674.2 | F42: =IF(A42=0,0,E42/A42) -> -5228.9141
A43: 400 | C43: =A43*$F$35+$F$23 -> -73050 | D43: =$F$29 -> -1204574.2 | E43: =C43+D43 -> -1277624.2 | F43: =IF(A43=0,0,E43/A43) -> -3194.0606
A44: 500 | C44: =A44*$F$35+$F$23 -> 218000 | D44: =$F$29 -> -1204574.2 | E44: =C44+D44 -> -986574.23 | F44: =IF(A44=0,0,E44/A44) -> -1973.1485
A45: 600 | C45: =A45*$F$35+$F$23 -> 509050 | D45: =$F$29 -> -1204574.2 | E45: =C45+D45 -> -695524.23 | F45: =IF(A45=0,0,E45/A45) -> -1159.207
A46: 700 | C46: =A46*$F$35+$F$23 -> 800100 | D46: =$F$29 -> -1204574.2 | E46: =C46+D46 -> -404474.23 | F46: =IF(A46=0,0,E46/A46) -> -577.82033
A47: 800 | C47: =A47*$F$35+$F$23 -> 1091150 | D47: =$F$29 -> -1204574.2 | E47: =C47+D47 -> -113424.23 | F47: =IF(A47=0,0,E47/A47) -> -141.78029
A48: 900 | C48: =A48*$F$35+$F$23 -> 1382200 | D48: =$F$29 -> -1204574.2 | E48: =C48+D48 -> 177625.77 | F48: =IF(A48=0,0,E48/A48) -> 197.36197

Sheet Financing Scenarios
A1: Financing scenarios: first aircraft, Live scenario
A2: How leverage changes cash needed and monthly cash flow. Change the LTV row (blue) to test other structures.
C4: Scenario 1 | D4: Scenario 2 | E4: Scenario 3 | F4: Scenario 4 | G4: Scenario 5 | H4: Scenario 6
A5: Loan-to-value | C5: 0.6 | D5: 0.7 | E5: 0.75 | F5: 0.8 | G5: 0.85 | H5: 0.9
A6: Purchase price | C6: =Assumptions!$F$7 -> 13500000 | D6: =Assumptions!$F$7 -> 13500000 | E6: =Assumptions!$F$7 -> 13500000 | F6: =Assumptions!$F$7 -> 13500000 | G6: =Assumptions!$F$7 -> 13500000 | H6: =Assumptions!$F$7 -> 13500000
A7: Loan | C7: =C6*C5 -> 8100000 | D7: =D6*D5 -> 9450000 | E7: =E6*E5 -> 10125000 | F7: =F6*F5 -> 10800000 | G7: =G6*G5 -> 11475000 | H7: =H6*H5 -> 12150000
A8: Down payment | C8: =C6-C7 -> 5400000 | D8: =D6-D7 -> 4050000 | E8: =E6-E7 -> 3375000 | F8: =F6-F7 -> 2700000 | G8: =G6-G7 -> 2025000 | H8: =H6-H7 -> 1350000
A9: Acquisition, onboarding and setup costs | C9: =Assumptions!$F$9+Assumptions!$F$10+Assumptions!$F$11+Assumptions!$F$12+Assumptions!$F$13+Assumptions!$F$14 -> 650000 | D9: =Assumptions!$F$9+Assumptions!$F$10+Assumptions!$F$11+Assumptions!$F$12+Assumptions!$F$13+Assumptions!$F$14 -> 650000 | E9: =Assumptions!$F$9+Assumptions!$F$10+Assumptions!$F$11+Assumptions!$F$12+Assumptions!$F$13+Assumptions!$F$14 -> 650000 | F9: =Assumptions!$F$9+Assumptions!$F$10+Assumptions!$F$11+Assumptions!$F$12+Assumptions!$F$13+Assumptions!$F$14 -> 650000 | G9: =Assumptions!$F$9+Assumptions!$F$10+Assumptions!$F$11+Assumptions!$F$12+Assumptions!$F$13+Assumptions!$F$14 -> 650000 | H9: =Assumptions!$F$9+Assumptions!$F$10+Assumptions!$F$11+Assumptions!$F$12+Assumptions!$F$13+Assumptions!$F$14 -> 650000
A10: Cash reserve | C10: ='Unit Economics'!$F$38 -> 618625 | D10: ='Unit Economics'!$F$38 -> 618625 | E10: ='Unit Economics'!$F$38 -> 618625 | F10: ='Unit Economics'!$F$38 -> 618625 | G10: ='Unit Economics'!$F$38 -> 618625 | H10: ='Unit Economics'!$F$38 -> 618625
A11: Total equity needed to launch | C11: =SUM(C8:C10) -> 6668625 | D11: =SUM(D8:D10) -> 5318625 | E11: =SUM(E8:E10) -> 4643625 | F11: =SUM(F8:F10) -> 3968625 | G11: =SUM(G8:G10) -> 3293625 | H11: =SUM(H8:H10) -> 2618625
A13: Annual debt service | C13: =PMT(Assumptions!$F$17,Assumptions!$F$18,-C7) -> 903430.67 | D13: =PMT(Assumptions!$F$17,Assumptions!$F$18,-D7) -> 1054002.5 | E13: =PMT(Assumptions!$F$17,Assumptions!$F$18,-E7) -> 1129288.3 | F13: =PMT(Assumptions!$F$17,Assumptions!$F$18,-F7) -> 1204574.2 | G13: =PMT(Assumptions!$F$17,Assumptions!$F$18,-G7) -> 1279860.1 | H13: =PMT(Assumptions!$F$17,Assumptions!$F$18,-H7) -> 1355146
A14: Monthly loan payment | C14: =C13/12 -> 75285.889 | D14: =D13/12 -> 87833.538 | E14: =E13/12 -> 94107.362 | F14: =F13/12 -> 100381.19 | G14: =G13/12 -> 106655.01 | H14: =H13/12 -> 112928.83
A15: Mature-year EBITDA (Unit Economics, Live) | C15: ='Unit Economics'!$F$25 -> 509050 | D15: ='Unit Economics'!$F$25 -> 509050 | E15: ='Unit Economics'!$F$25 -> 509050 | F15: ='Unit Economics'!$F$25 -> 509050 | G15: ='Unit Economics'!$F$25 -> 509050 | H15: ='Unit Economics'!$F$25 -> 509050
A16: Cash flow after debt service | C16: =C15-C13 -> -394380.67 | D16: =D15-D13 -> -544952.45 | E16: =E15-E13 -> -620238.34 | F16: =F15-F13 -> -695524.23 | G16: =G15-G13 -> -770810.12 | H16: =H15-H13 -> -846096.01
A17: Debt service coverage (EBITDA / debt service) | C17: =IF(C13=0,0,C15/C13) -> 0.56346327 | D17: =IF(D13=0,0,D15/D13) -> 0.48296852 | E17: =IF(E13=0,0,E15/E13) -> 0.45077062 | F17: =IF(F13=0,0,F15/F13) -> 0.42259745 | G17: =IF(G13=0,0,G15/G13) -> 0.39773878 | H17: =IF(H13=0,0,H15/H13) -> 0.37564218
A18: Cash-on-cash return | C18: =IF(C11=0,0,C16/C11) -> -0.059139729 | D18: =IF(D11=0,0,D16/D11) -> -0.10246115 | E18: =IF(E11=0,0,E16/E11) -> -0.13356771 | F18: =IF(F11=0,0,F16/F11) -> -0.17525572 | G18: =IF(G11=0,0,G16/G11) -> -0.23403093 | H18: =IF(H11=0,0,H16/H11) -> -0.32310698
A19: Breakeven billable hours incl. debt service | C19: =IF('Unit Economics'!$F$35<=0,0,(-'Unit Economics'!$F$23+C13)/'Unit Economics'!$F$35) -> 735.50272 | D19: =IF('Unit Economics'!$F$35<=0,0,(-'Unit Economics'!$F$23+D13)/'Unit Economics'!$F$35) -> 787.23671 | E19: =IF('Unit Economics'!$F$35<=0,0,(-'Unit Economics'!$F$23+E13)/'Unit Economics'!$F$35) -> 813.10371 | F19: =IF('Unit Economics'!$F$35<=0,0,(-'Unit Economics'!$F$23+F13)/'Unit Economics'!$F$35) -> 838.9707 | G19: =IF('Unit Economics'!$F$35<=0,0,(-'Unit Economics'!$F$23+G13)/'Unit Economics'!$F$35) -> 864.8377 | H19: =IF('Unit Economics'!$F$35<=0,0,(-'Unit Economics'!$F$23+H13)/'Unit Economics'!$F$35) -> 890.70469
A21: Lender reality check
A22: Credit-based jet loans typically need 15-20% down (80-85% LTV); asset-based loans 30-40% down (AOPA via flycraft.com).
A23: 85-90% leverage usually means a personal guarantee, strong outside liquidity, or a second-lien / seller note on top of the senior loan.
A24: Lenders want DSCR of about 1.25x on the business alone, or will underwrite Henry's personal income and liquidity instead.
A26: Cash flow after debt service: billable hours (rows) by LTV (columns)
A27: Billable hours | C27: =C5 -> 0.6 | D27: =D5 -> 0.7 | E27: =E5 -> 0.75 | F27: =F5 -> 0.8 | G27: =G5 -> 0.85 | H27: =H5 -> 0.9
A28: 400 | C28: =$A28*'Unit Economics'!$F$35+'Unit Economics'!$F$23-C$13 -> -976480.67 | D28: =$A28*'Unit Economics'!$F$35+'Unit Economics'!$F$23-D$13 -> -1127052.5 | E28: =$A28*'Unit Economics'!$F$35+'Unit Economics'!$F$23-E$13 -> -1202338.3 | F28: =$A28*'Unit Economics'!$F$35+'Unit Economics'!$F$23-F$13 -> -1277624.2 | G28: =$A28*'Unit Economics'!$F$35+'Unit Economics'!$F$23-G$13 -> -1352910.1 | H28: =$A28*'Unit Economics'!$F$35+'Unit Economics'!$F$23-H$13 -> -1428196
A29: 500 | C29: =$A29*'Unit Economics'!$F$35+'Unit Economics'!$F$23-C$13 -> -685430.67 | D29: =$A29*'Unit Economics'!$F$35+'Unit Economics'!$F$23-D$13 -> -836002.45 | E29: =$A29*'Unit Economics'!$F$35+'Unit Economics'!$F$23-E$13 -> -911288.34 | F29: =$A29*'Unit Economics'!$F$35+'Unit Economics'!$F$23-F$13 -> -986574.23 | G29: =$A29*'Unit Economics'!$F$35+'Unit Economics'!$F$23-G$13 -> -1061860.1 | H29: =$A29*'Unit Economics'!$F$35+'Unit Economics'!$F$23-H$13 -> -1137146
A30: 600 | C30: =$A30*'Unit Economics'!$F$35+'Unit Economics'!$F$23-C$13 -> -394380.67 | D30: =$A30*'Unit Economics'!$F$35+'Unit Economics'!$F$23-D$13 -> -544952.45 | E30: =$A30*'Unit Economics'!$F$35+'Unit Economics'!$F$23-E$13 -> -620238.34 | F30: =$A30*'Unit Economics'!$F$35+'Unit Economics'!$F$23-F$13 -> -695524.23 | G30: =$A30*'Unit Economics'!$F$35+'Unit Economics'!$F$23-G$13 -> -770810.12 | H30: =$A30*'Unit Economics'!$F$35+'Unit Economics'!$F$23-H$13 -> -846096.01
A31: 700 | C31: =$A31*'Unit Economics'!$F$35+'Unit Economics'!$F$23-C$13 -> -103330.67 | D31: =$A31*'Unit Economics'!$F$35+'Unit Economics'!$F$23-D$13 -> -253902.45 | E31: =$A31*'Unit Economics'!$F$35+'Unit Economics'!$F$23-E$13 -> -329188.34 | F31: =$A31*'Unit Economics'!$F$35+'Unit Economics'!$F$23-F$13 -> -404474.23 | G31: =$A31*'Unit Economics'!$F$35+'Unit Economics'!$F$23-G$13 -> -479760.12 | H31: =$A31*'Unit Economics'!$F$35+'Unit Economics'!$F$23-H$13 -> -555046.01
A32: 800 | C32: =$A32*'Unit Economics'!$F$35+'Unit Economics'!$F$23-C$13 -> 187719.33 | D32: =$A32*'Unit Economics'!$F$35+'Unit Economics'!$F$23-D$13 -> 37147.549 | E32: =$A32*'Unit Economics'!$F$35+'Unit Economics'!$F$23-E$13 -> -38138.34 | F32: =$A32*'Unit Economics'!$F$35+'Unit Economics'!$F$23-F$13 -> -113424.23 | G32: =$A32*'Unit Economics'!$F$35+'Unit Economics'!$F$23-G$13 -> -188710.12 | H32: =$A32*'Unit Economics'!$F$35+'Unit Economics'!$F$23-H$13 -> -263996.01
A33: 900 | C33: =$A33*'Unit Economics'!$F$35+'Unit Economics'!$F$23-C$13 -> 478769.33 | D33: =$A33*'Unit Economics'!$F$35+'Unit Economics'!$F$23-D$13 -> 328197.55 | E33: =$A33*'Unit Economics'!$F$35+'Unit Economics'!$F$23-E$13 -> 252911.66 | F33: =$A33*'Unit Economics'!$F$35+'Unit Economics'!$F$23-F$13 -> 177625.77 | G33: =$A33*'Unit Economics'!$F$35+'Unit Economics'!$F$23-G$13 -> 102339.88 | H33: =$A33*'Unit Economics'!$F$35+'Unit Economics'!$F$23-H$13 -> 27053.992

Sheet Debt Schedule
A1: Debt and aircraft value schedule by owned aircraft
A2: Each owned aircraft gets its own loan at the Live LTV and rate. Payments start in the purchase year (conservative).
A4: Item | C4: 2027 | D4: 2028 | E4: 2029 | F4: 2030 | G4: 2031 | H4: 2032 | I4: 2033 | J4: 2034 | K4: 2035 | L4: 2036
A5: Year | C5: 2027 | D5: 2028 | E5: 2029 | F5: 2030 | G5: 2031 | H5: 2032 | I5: 2033 | J5: 2034 | K5: 2035 | L5: 2036
A7: Aircraft #1
A8: Purchase year | B8: =2027+COUNTIF('Fleet Plan'!$C$9:$L$9,"<1") -> 2027
A9: Price paid | B9: =IF($B$8>2036,0,Assumptions!$F$7*(1+Assumptions!$F$8)^($B$8-2027)) -> 13500000
A10: Loan | B10: =$B$9*Assumptions!$F$16 -> 10800000
A11: Annual payment | B11: =IF($B$10=0,0,PMT(Assumptions!$F$17,Assumptions!$F$18,-$B$10)) -> 1204574.2
A12: Beginning balance | C12: =IF(C$5=$B$8,$B$10,IF(C$5>$B$8,0,0)) -> 10800000 | D12: =IF(D$5=$B$8,$B$10,IF(D$5>$B$8,C16,0)) -> 10378426 | E12: =IF(E$5=$B$8,$B$10,IF(E$5>$B$8,D16,0)) -> 9926287.4 | F12: =IF(F$5=$B$8,$B$10,IF(F$5>$B$8,E16,0)) -> 9441369 | G12: =IF(G$5=$B$8,$B$10,IF(G$5>$B$8,F16,0)) -> 8921294 | H12: =IF(H$5=$B$8,$B$10,IF(H$5>$B$8,G16,0)) -> 8363513.6 | I12: =IF(I$5=$B$8,$B$10,IF(I$5>$B$8,H16,0)) -> 7765294.1 | J12: =IF(J$5=$B$8,$B$10,IF(J$5>$B$8,I16,0)) -> 7123703.7 | K12: =IF(K$5=$B$8,$B$10,IF(K$5>$B$8,J16,0)) -> 6435598 | L12: =IF(L$5=$B$8,$B$10,IF(L$5>$B$8,K16,0)) -> 5697604.7
A13: Interest | C13: =C12*Assumptions!$F$17 -> 783000 | D13: =D12*Assumptions!$F$17 -> 752435.87 | E13: =E12*Assumptions!$F$17 -> 719655.84 | F13: =F12*Assumptions!$F$17 -> 684499.25 | G13: =G12*Assumptions!$F$17 -> 646793.82 | H13: =H12*Assumptions!$F$17 -> 606354.74 | I13: =I12*Assumptions!$F$17 -> 562983.83 | J13: =J12*Assumptions!$F$17 -> 516468.52 | ... L13: =L12*Assumptions!$F$17 -> 413076.34
A14: Payment | C14: =IF(C12>0,MIN($B$11,C12+C13),0) -> 1204574.2 | D14: =IF(D12>0,MIN($B$11,D12+D13),0) -> 1204574.2 | E14: =IF(E12>0,MIN($B$11,E12+E13),0) -> 1204574.2 | F14: =IF(F12>0,MIN($B$11,F12+F13),0) -> 1204574.2 | G14: =IF(G12>0,MIN($B$11,G12+G13),0) -> 1204574.2 | H14: =IF(H12>0,MIN($B$11,H12+H13),0) -> 1204574.2 | I14: =IF(I12>0,MIN($B$11,I12+I13),0) -> 1204574.2 | J14: =IF(J12>0,MIN($B$11,J12+J13),0) -> 1204574.2 | ... L14: =IF(L12>0,MIN($B$11,L12+L13),0) -> 1204574.2
A15: Principal | C15: =C14-C13 -> 421574.23 | D15: =D14-D13 -> 452138.36 | E15: =E14-E13 -> 484918.39 | F15: =F14-F13 -> 520074.98 | G15: =G14-G13 -> 557780.41 | H15: =H14-H13 -> 598219.49 | I15: =I14-I13 -> 641590.4 | J15: =J14-J13 -> 688105.71 | ... L15: =L14-L13 -> 791497.89
A16: Ending balance | C16: =C12-C15 -> 10378426 | D16: =D12-D15 -> 9926287.4 | E16: =E12-E15 -> 9441369 | F16: =F12-F15 -> 8921294 | G16: =G12-G15 -> 8363513.6 | H16: =H12-H15 -> 7765294.1 | I16: =I12-I15 -> 7123703.7 | J16: =J12-J15 -> 6435598 | ... L16: =L12-L15 -> 4906106.8
A17: Market value (year end) | C17: =IF(C$5>=$B$8,$B$9*(1-Assumptions!$F$63)^(C$5-$B$8+1),0) -> 12825000 | D17: =IF(D$5>=$B$8,$B$9*(1-Assumptions!$F$63)^(D$5-$B$8+1),0) -> 12183750 | E17: =IF(E$5>=$B$8,$B$9*(1-Assumptions!$F$63)^(E$5-$B$8+1),0) -> 11574562 | F17: =IF(F$5>=$B$8,$B$9*(1-Assumptions!$F$63)^(F$5-$B$8+1),0) -> 10995834 | G17: =IF(G$5>=$B$8,$B$9*(1-Assumptions!$F$63)^(G$5-$B$8+1),0) -> 10446043 | H17: =IF(H$5>=$B$8,$B$9*(1-Assumptions!$F$63)^(H$5-$B$8+1),0) -> 9923740.5 | I17: =IF(I$5>=$B$8,$B$9*(1-Assumptions!$F$63)^(I$5-$B$8+1),0) -> 9427553.5 | J17: =IF(J$5>=$B$8,$B$9*(1-Assumptions!$F$63)^(J$5-$B$8+1),0) -> 8956175.8 | ... L17: =IF(L$5>=$B$8,$B$9*(1-Assumptions!$F$63)^(L$5-$B$8+1),0) -> 8082948.7
A19: Aircraft #2
A20: Purchase year | B20: =2027+COUNTIF('Fleet Plan'!$C$9:$L$9,"<2") -> 2030
A21: Price paid | B21: =IF($B$20>2036,0,Assumptions!$F$7*(1+Assumptions!$F$8)^($B$20-2027)) -> 13500000
A22: Loan | B22: =$B$21*Assumptions!$F$16 -> 10800000
A23: Annual payment | B23: =IF($B$22=0,0,PMT(Assumptions!$F$17,Assumptions!$F$18,-$B$22)) -> 1204574.2
A24: Beginning balance | C24: =IF(C$5=$B$20,$B$22,IF(C$5>$B$20,0,0)) -> 0 | D24: =IF(D$5=$B$20,$B$22,IF(D$5>$B$20,C28,0)) -> 0 | E24: =IF(E$5=$B$20,$B$22,IF(E$5>$B$20,D28,0)) -> 0 | F24: =IF(F$5=$B$20,$B$22,IF(F$5>$B$20,E28,0)) -> 10800000 | G24: =IF(G$5=$B$20,$B$22,IF(G$5>$B$20,F28,0)) -> 10378426 | H24: =IF(H$5=$B$20,$B$22,IF(H$5>$B$20,G28,0)) -> 9926287.4 | I24: =IF(I$5=$B$20,$B$22,IF(I$5>$B$20,H28,0)) -> 9441369 | J24: =IF(J$5=$B$20,$B$22,IF(J$5>$B$20,I28,0)) -> 8921294 | K24: =IF(K$5=$B$20,$B$22,IF(K$5>$B$20,J28,0)) -> 8363513.6 | L24: =IF(L$5=$B$20,$B$22,IF(L$5>$B$20,K28,0)) -> 7765294.1
A25: Interest | C25: =C24*Assumptions!$F$17 -> 0 | D25: =D24*Assumptions!$F$17 -> 0 | E25: =E24*Assumptions!$F$17 -> 0 | F25: =F24*Assumptions!$F$17 -> 783000 | G25: =G24*Assumptions!$F$17 -> 752435.87 | H25: =H24*Assumptions!$F$17 -> 719655.84 | I25: =I24*Assumptions!$F$17 -> 684499.25 | J25: =J24*Assumptions!$F$17 -> 646793.82 | ... L25: =L24*Assumptions!$F$17 -> 562983.83
A26: Payment | C26: =IF(C24>0,MIN($B$23,C24+C25),0) -> 0 | D26: =IF(D24>0,MIN($B$23,D24+D25),0) -> 0 | E26: =IF(E24>0,MIN($B$23,E24+E25),0) -> 0 | F26: =IF(F24>0,MIN($B$23,F24+F25),0) -> 1204574.2 | G26: =IF(G24>0,MIN($B$23,G24+G25),0) -> 1204574.2 | H26: =IF(H24>0,MIN($B$23,H24+H25),0) -> 1204574.2 | I26: =IF(I24>0,MIN($B$23,I24+I25),0) -> 1204574.2 | J26: =IF(J24>0,MIN($B$23,J24+J25),0) -> 1204574.2 | ... L26: =IF(L24>0,MIN($B$23,L24+L25),0) -> 1204574.2
A27: Principal | C27: =C26-C25 -> 0 | D27: =D26-D25 -> 0 | E27: =E26-E25 -> 0 | F27: =F26-F25 -> 421574.23 | G27: =G26-G25 -> 452138.36 | H27: =H26-H25 -> 484918.39 | I27: =I26-I25 -> 520074.98 | J27: =J26-J25 -> 557780.41 | ... L27: =L26-L25 -> 641590.4
A28: Ending balance | C28: =C24-C27 -> 0 | D28: =D24-D27 -> 0 | E28: =E24-E27 -> 0 | F28: =F24-F27 -> 10378426 | G28: =G24-G27 -> 9926287.4 | H28: =H24-H27 -> 9441369 | I28: =I24-I27 -> 8921294 | J28: =J24-J27 -> 8363513.6 | ... L28: =L24-L27 -> 7123703.7
A29: Market value (year end) | C29: =IF(C$5>=$B$20,$B$21*(1-Assumptions!$F$63)^(C$5-$B$20+1),0) -> 0 | D29: =IF(D$5>=$B$20,$B$21*(1-Assumptions!$F$63)^(D$5-$B$20+1),0) -> 0 | E29: =IF(E$5>=$B$20,$B$21*(1-Assumptions!$F$63)^(E$5-$B$20+1),0) -> 0 | F29: =IF(F$5>=$B$20,$B$21*(1-Assumptions!$F$63)^(F$5-$B$20+1),0) -> 12825000 | G29: =IF(G$5>=$B$20,$B$21*(1-Assumptions!$F$63)^(G$5-$B$20+1),0) -> 12183750 | H29: =IF(H$5>=$B$20,$B$21*(1-Assumptions!$F$63)^(H$5-$B$20+1),0) -> 11574562 | I29: =IF(I$5>=$B$20,$B$21*(1-Assumptions!$F$63)^(I$5-$B$20+1),0) -> 10995834 | J29: =IF(J$5>=$B$20,$B$21*(1-Assumptions!$F$63)^(J$5-$B$20+1),0) -> 10446043 | ... L29: =IF(L$5>=$B$20,$B$21*(1-Assumptions!$F$63)^(L$5-$B$20+1),0) -> 9427553.5
A31: Aircraft #3
A32: Purchase year | B32: =2027+COUNTIF('Fleet Plan'!$C$9:$L$9,"<3") -> 2033
A33: Price paid | B33: =IF($B$32>2036,0,Assumptions!$F$7*(1+Assumptions!$F$8)^($B$32-2027)) -> 13500000
A34: Loan | B34: =$B$33*Assumptions!$F$16 -> 10800000
A35: Annual payment | B35: =IF($B$34=0,0,PMT(Assumptions!$F$17,Assumptions!$F$18,-$B$34)) -> 1204574.2
A36: Beginning balance | C36: =IF(C$5=$B$32,$B$34,IF(C$5>$B$32,0,0)) -> 0 | D36: =IF(D$5=$B$32,$B$34,IF(D$5>$B$32,C40,0)) -> 0 | E36: =IF(E$5=$B$32,$B$34,IF(E$5>$B$32,D40,0)) -> 0 | F36: =IF(F$5=$B$32,$B$34,IF(F$5>$B$32,E40,0)) -> 0 | G36: =IF(G$5=$B$32,$B$34,IF(G$5>$B$32,F40,0)) -> 0 | H36: =IF(H$5=$B$32,$B$34,IF(H$5>$B$32,G40,0)) -> 0 | I36: =IF(I$5=$B$32,$B$34,IF(I$5>$B$32,H40,0)) -> 10800000 | J36: =IF(J$5=$B$32,$B$34,IF(J$5>$B$32,I40,0)) -> 10378426 | K36: =IF(K$5=$B$32,$B$34,IF(K$5>$B$32,J40,0)) -> 9926287.4 | L36: =IF(L$5=$B$32,$B$34,IF(L$5>$B$32,K40,0)) -> 9441369
A37: Interest | C37: =C36*Assumptions!$F$17 -> 0 | D37: =D36*Assumptions!$F$17 -> 0 | E37: =E36*Assumptions!$F$17 -> 0 | F37: =F36*Assumptions!$F$17 -> 0 | G37: =G36*Assumptions!$F$17 -> 0 | H37: =H36*Assumptions!$F$17 -> 0 | I37: =I36*Assumptions!$F$17 -> 783000 | J37: =J36*Assumptions!$F$17 -> 752435.87 | ... L37: =L36*Assumptions!$F$17 -> 684499.25
A38: Payment | C38: =IF(C36>0,MIN($B$35,C36+C37),0) -> 0 | D38: =IF(D36>0,MIN($B$35,D36+D37),0) -> 0 | E38: =IF(E36>0,MIN($B$35,E36+E37),0) -> 0 | F38: =IF(F36>0,MIN($B$35,F36+F37),0) -> 0 | G38: =IF(G36>0,MIN($B$35,G36+G37),0) -> 0 | H38: =IF(H36>0,MIN($B$35,H36+H37),0) -> 0 | I38: =IF(I36>0,MIN($B$35,I36+I37),0) -> 1204574.2 | J38: =IF(J36>0,MIN($B$35,J36+J37),0) -> 1204574.2 | ... L38: =IF(L36>0,MIN($B$35,L36+L37),0) -> 1204574.2
A39: Principal | C39: =C38-C37 -> 0 | D39: =D38-D37 -> 0 | E39: =E38-E37 -> 0 | F39: =F38-F37 -> 0 | G39: =G38-G37 -> 0 | H39: =H38-H37 -> 0 | I39: =I38-I37 -> 421574.23 | J39: =J38-J37 -> 452138.36 | ... L39: =L38-L37 -> 520074.98
A40: Ending balance | C40: =C36-C39 -> 0 | D40: =D36-D39 -> 0 | E40: =E36-E39 -> 0 | F40: =F36-F39 -> 0 | G40: =G36-G39 -> 0 | H40: =H36-H39 -> 0 | I40: =I36-I39 -> 10378426 | J40: =J36-J39 -> 9926287.4 | ... L40: =L36-L39 -> 8921294
A41: Market value (year end) | C41: =IF(C$5>=$B$32,$B$33*(1-Assumptions!$F$63)^(C$5-$B$32+1),0) -> 0 | D41: =IF(D$5>=$B$32,$B$33*(1-Assumptions!$F$63)^(D$5-$B$32+1),0) -> 0 | E41: =IF(E$5>=$B$32,$B$33*(1-Assumptions!$F$63)^(E$5-$B$32+1),0) -> 0 | F41: =IF(F$5>=$B$32,$B$33*(1-Assumptions!$F$63)^(F$5-$B$32+1),0) -> 0 | G41: =IF(G$5>=$B$32,$B$33*(1-Assumptions!$F$63)^(G$5-$B$32+1),0) -> 0 | H41: =IF(H$5>=$B$32,$B$33*(1-Assumptions!$F$63)^(H$5-$B$32+1),0) -> 0 | I41: =IF(I$5>=$B$32,$B$33*(1-Assumptions!$F$63)^(I$5-$B$32+1),0) -> 12825000 | J41: =IF(J$5>=$B$32,$B$33*(1-Assumptions!$F$63)^(J$5-$B$32+1),0) -> 12183750 | ... L41: =IF(L$5>=$B$32,$B$33*(1-Assumptions!$F$63)^(L$5-$B$32+1),0) -> 10995834
A43: Aircraft #4
A44: Purchase year | B44: =2027+COUNTIF('Fleet Plan'!$C$9:$L$9,"<4") -> 2037
A45: Price paid | B45: =IF($B$44>2036,0,Assumptions!$F$7*(1+Assumptions!$F$8)^($B$44-2027)) -> 0
A46: Loan | B46: =$B$45*Assumptions!$F$16 -> 0
A47: Annual payment | B47: =IF($B$46=0,0,PMT(Assumptions!$F$17,Assumptions!$F$18,-$B$46)) -> 0
A48: Beginning balance | C48: =IF(C$5=$B$44,$B$46,IF(C$5>$B$44,0,0)) -> 0 | D48: =IF(D$5=$B$44,$B$46,IF(D$5>$B$44,C52,0)) -> 0 | E48: =IF(E$5=$B$44,$B$46,IF(E$5>$B$44,D52,0)) -> 0 | F48: =IF(F$5=$B$44,$B$46,IF(F$5>$B$44,E52,0)) -> 0 | G48: =IF(G$5=$B$44,$B$46,IF(G$5>$B$44,F52,0)) -> 0 | H48: =IF(H$5=$B$44,$B$46,IF(H$5>$B$44,G52,0)) -> 0 | I48: =IF(I$5=$B$44,$B$46,IF(I$5>$B$44,H52,0)) -> 0 | J48: =IF(J$5=$B$44,$B$46,IF(J$5>$B$44,I52,0)) -> 0 | K48: =IF(K$5=$B$44,$B$46,IF(K$5>$B$44,J52,0)) -> 0 | L48: =IF(L$5=$B$44,$B$46,IF(L$5>$B$44,K52,0)) -> 0
A49: Interest | C49: =C48*Assumptions!$F$17 -> 0 | D49: =D48*Assumptions!$F$17 -> 0 | E49: =E48*Assumptions!$F$17 -> 0 | F49: =F48*Assumptions!$F$17 -> 0 | G49: =G48*Assumptions!$F$17 -> 0 | H49: =H48*Assumptions!$F$17 -> 0 | I49: =I48*Assumptions!$F$17 -> 0 | J49: =J48*Assumptions!$F$17 -> 0 | ... L49: =L48*Assumptions!$F$17 -> 0
A50: Payment | C50: =IF(C48>0,MIN($B$47,C48+C49),0) -> 0 | D50: =IF(D48>0,MIN($B$47,D48+D49),0) -> 0 | E50: =IF(E48>0,MIN($B$47,E48+E49),0) -> 0 | F50: =IF(F48>0,MIN($B$47,F48+F49),0) -> 0 | G50: =IF(G48>0,MIN($B$47,G48+G49),0) -> 0 | H50: =IF(H48>0,MIN($B$47,H48+H49),0) -> 0 | I50: =IF(I48>0,MIN($B$47,I48+I49),0) -> 0 | J50: =IF(J48>0,MIN($B$47,J48+J49),0) -> 0 | ... L50: =IF(L48>0,MIN($B$47,L48+L49),0) -> 0
A51: Principal | C51: =C50-C49 -> 0 | D51: =D50-D49 -> 0 | E51: =E50-E49 -> 0 | F51: =F50-F49 -> 0 | G51: =G50-G49 -> 0 | H51: =H50-H49 -> 0 | I51: =I50-I49 -> 0 | J51: =J50-J49 -> 0 | ... L51: =L50-L49 -> 0
A52: Ending balance | C52: =C48-C51 -> 0 | D52: =D48-D51 -> 0 | E52: =E48-E51 -> 0 | F52: =F48-F51 -> 0 | G52: =G48-G51 -> 0 | H52: =H48-H51 -> 0 | I52: =I48-I51 -> 0 | J52: =J48-J51 -> 0 | ... L52: =L48-L51 -> 0
A53: Market value (year end) | C53: =IF(C$5>=$B$44,$B$45*(1-Assumptions!$F$63)^(C$5-$B$44+1),0) -> 0 | D53: =IF(D$5>=$B$44,$B$45*(1-Assumptions!$F$63)^(D$5-$B$44+1),0) -> 0 | E53: =IF(E$5>=$B$44,$B$45*(1-Assumptions!$F$63)^(E$5-$B$44+1),0) -> 0 | F53: =IF(F$5>=$B$44,$B$45*(1-Assumptions!$F$63)^(F$5-$B$44+1),0) -> 0 | G53: =IF(G$5>=$B$44,$B$45*(1-Assumptions!$F$63)^(G$5-$B$44+1),0) -> 0 | H53: =IF(H$5>=$B$44,$B$45*(1-Assumptions!$F$63)^(H$5-$B$44+1),0) -> 0 | I53: =IF(I$5>=$B$44,$B$45*(1-Assumptions!$F$63)^(I$5-$B$44+1),0) -> 0 | J53: =IF(J$5>=$B$44,$B$45*(1-Assumptions!$F$63)^(J$5-$B$44+1),0) -> 0 | ... L53: =IF(L$5>=$B$44,$B$45*(1-Assumptions!$F$63)^(L$5-$B$44+1),0) -> 0
A55: Aircraft #5
A56: Purchase year | B56: =2027+COUNTIF('Fleet Plan'!$C$9:$L$9,"<5") -> 2037
A57: Price paid | B57: =IF($B$56>2036,0,Assumptions!$F$7*(1+Assumptions!$F$8)^($B$56-2027)) -> 0
A58: Loan | B58: =$B$57*Assumptions!$F$16 -> 0
A59: Annual payment | B59: =IF($B$58=0,0,PMT(Assumptions!$F$17,Assumptions!$F$18,-$B$58)) -> 0
A60: Beginning balance | C60: =IF(C$5=$B$56,$B$58,IF(C$5>$B$56,0,0)) -> 0 | D60: =IF(D$5=$B$56,$B$58,IF(D$5>$B$56,C64,0)) -> 0 | E60: =IF(E$5=$B$56,$B$58,IF(E$5>$B$56,D64,0)) -> 0 | F60: =IF(F$5=$B$56,$B$58,IF(F$5>$B$56,E64,0)) -> 0 | G60: =IF(G$5=$B$56,$B$58,IF(G$5>$B$56,F64,0)) -> 0 | H60: =IF(H$5=$B$56,$B$58,IF(H$5>$B$56,G64,0)) -> 0 | I60: =IF(I$5=$B$56,$B$58,IF(I$5>$B$56,H64,0)) -> 0 | J60: =IF(J$5=$B$56,$B$58,IF(J$5>$B$56,I64,0)) -> 0 | K60: =IF(K$5=$B$56,$B$58,IF(K$5>$B$56,J64,0)) -> 0 | L60: =IF(L$5=$B$56,$B$58,IF(L$5>$B$56,K64,0)) -> 0
A61: Interest | C61: =C60*Assumptions!$F$17 -> 0 | D61: =D60*Assumptions!$F$17 -> 0 | E61: =E60*Assumptions!$F$17 -> 0 | F61: =F60*Assumptions!$F$17 -> 0 | G61: =G60*Assumptions!$F$17 -> 0 | H61: =H60*Assumptions!$F$17 -> 0 | I61: =I60*Assumptions!$F$17 -> 0 | J61: =J60*Assumptions!$F$17 -> 0 | ... L61: =L60*Assumptions!$F$17 -> 0
A62: Payment | C62: =IF(C60>0,MIN($B$59,C60+C61),0) -> 0 | D62: =IF(D60>0,MIN($B$59,D60+D61),0) -> 0 | E62: =IF(E60>0,MIN($B$59,E60+E61),0) -> 0 | F62: =IF(F60>0,MIN($B$59,F60+F61),0) -> 0 | G62: =IF(G60>0,MIN($B$59,G60+G61),0) -> 0 | H62: =IF(H60>0,MIN($B$59,H60+H61),0) -> 0 | I62: =IF(I60>0,MIN($B$59,I60+I61),0) -> 0 | J62: =IF(J60>0,MIN($B$59,J60+J61),0) -> 0 | ... L62: =IF(L60>0,MIN($B$59,L60+L61),0) -> 0
A63: Principal | C63: =C62-C61 -> 0 | D63: =D62-D61 -> 0 | E63: =E62-E61 -> 0 | F63: =F62-F61 -> 0 | G63: =G62-G61 -> 0 | H63: =H62-H61 -> 0 | I63: =I62-I61 -> 0 | J63: =J62-J61 -> 0 | ... L63: =L62-L61 -> 0
A64: Ending balance | C64: =C60-C63 -> 0 | D64: =D60-D63 -> 0 | E64: =E60-E63 -> 0 | F64: =F60-F63 -> 0 | G64: =G60-G63 -> 0 | H64: =H60-H63 -> 0 | I64: =I60-I63 -> 0 | J64: =J60-J63 -> 0 | ... L64: =L60-L63 -> 0
A65: Market value (year end) | C65: =IF(C$5>=$B$56,$B$57*(1-Assumptions!$F$63)^(C$5-$B$56+1),0) -> 0 | D65: =IF(D$5>=$B$56,$B$57*(1-Assumptions!$F$63)^(D$5-$B$56+1),0) -> 0 | E65: =IF(E$5>=$B$56,$B$57*(1-Assumptions!$F$63)^(E$5-$B$56+1),0) -> 0 | F65: =IF(F$5>=$B$56,$B$57*(1-Assumptions!$F$63)^(F$5-$B$56+1),0) -> 0 | G65: =IF(G$5>=$B$56,$B$57*(1-Assumptions!$F$63)^(G$5-$B$56+1),0) -> 0 | H65: =IF(H$5>=$B$56,$B$57*(1-Assumptions!$F$63)^(H$5-$B$56+1),0) -> 0 | I65: =IF(I$5>=$B$56,$B$57*(1-Assumptions!$F$63)^(I$5-$B$56+1),0) -> 0 | J65: =IF(J$5>=$B$56,$B$57*(1-Assumptions!$F$63)^(J$5-$B$56+1),0) -> 0 | ... L65: =IF(L$5>=$B$56,$B$57*(1-Assumptions!$F$63)^(L$5-$B$56+1),0) -> 0
A67: Aircraft #6
A68: Purchase year | B68: =2027+COUNTIF('Fleet Plan'!$C$9:$L$9,"<6") -> 2037
A69: Price paid | B69: =IF($B$68>2036,0,Assumptions!$F$7*(1+Assumptions!$F$8)^($B$68-2027)) -> 0
A70: Loan | B70: =$B$69*Assumptions!$F$16 -> 0
A71: Annual payment | B71: =IF($B$70=0,0,PMT(Assumptions!$F$17,Assumptions!$F$18,-$B$70)) -> 0
A72: Beginning balance | C72: =IF(C$5=$B$68,$B$70,IF(C$5>$B$68,0,0)) -> 0 | D72: =IF(D$5=$B$68,$B$70,IF(D$5>$B$68,C76,0)) -> 0 | E72: =IF(E$5=$B$68,$B$70,IF(E$5>$B$68,D76,0)) -> 0 | F72: =IF(F$5=$B$68,$B$70,IF(F$5>$B$68,E76,0)) -> 0 | G72: =IF(G$5=$B$68,$B$70,IF(G$5>$B$68,F76,0)) -> 0 | H72: =IF(H$5=$B$68,$B$70,IF(H$5>$B$68,G76,0)) -> 0 | I72: =IF(I$5=$B$68,$B$70,IF(I$5>$B$68,H76,0)) -> 0 | J72: =IF(J$5=$B$68,$B$70,IF(J$5>$B$68,I76,0)) -> 0 | K72: =IF(K$5=$B$68,$B$70,IF(K$5>$B$68,J76,0)) -> 0 | L72: =IF(L$5=$B$68,$B$70,IF(L$5>$B$68,K76,0)) -> 0
A73: Interest | C73: =C72*Assumptions!$F$17 -> 0 | D73: =D72*Assumptions!$F$17 -> 0 | E73: =E72*Assumptions!$F$17 -> 0 | F73: =F72*Assumptions!$F$17 -> 0 | G73: =G72*Assumptions!$F$17 -> 0 | H73: =H72*Assumptions!$F$17 -> 0 | I73: =I72*Assumptions!$F$17 -> 0 | J73: =J72*Assumptions!$F$17 -> 0 | ... L73: =L72*Assumptions!$F$17 -> 0
A74: Payment | C74: =IF(C72>0,MIN($B$71,C72+C73),0) -> 0 | D74: =IF(D72>0,MIN($B$71,D72+D73),0) -> 0 | E74: =IF(E72>0,MIN($B$71,E72+E73),0) -> 0 | F74: =IF(F72>0,MIN($B$71,F72+F73),0) -> 0 | G74: =IF(G72>0,MIN($B$71,G72+G73),0) -> 0 | H74: =IF(H72>0,MIN($B$71,H72+H73),0) -> 0 | I74: =IF(I72>0,MIN($B$71,I72+I73),0) -> 0 | J74: =IF(J72>0,MIN($B$71,J72+J73),0) -> 0 | ... L74: =IF(L72>0,MIN($B$71,L72+L73),0) -> 0
A75: Principal | C75: =C74-C73 -> 0 | D75: =D74-D73 -> 0 | E75: =E74-E73 -> 0 | F75: =F74-F73 -> 0 | G75: =G74-G73 -> 0 | H75: =H74-H73 -> 0 | I75: =I74-I73 -> 0 | J75: =J74-J73 -> 0 | ... L75: =L74-L73 -> 0
A76: Ending balance | C76: =C72-C75 -> 0 | D76: =D72-D75 -> 0 | E76: =E72-E75 -> 0 | F76: =F72-F75 -> 0 | G76: =G72-G75 -> 0 | H76: =H72-H75 -> 0 | I76: =I72-I75 -> 0 | J76: =J72-J75 -> 0 | ... L76: =L72-L75 -> 0
A77: Market value (year end) | C77: =IF(C$5>=$B$68,$B$69*(1-Assumptions!$F$63)^(C$5-$B$68+1),0) -> 0 | D77: =IF(D$5>=$B$68,$B$69*(1-Assumptions!$F$63)^(D$5-$B$68+1),0) -> 0 | E77: =IF(E$5>=$B$68,$B$69*(1-Assumptions!$F$63)^(E$5-$B$68+1),0) -> 0 | F77: =IF(F$5>=$B$68,$B$69*(1-Assumptions!$F$63)^(F$5-$B$68+1),0) -> 0 | G77: =IF(G$5>=$B$68,$B$69*(1-Assumptions!$F$63)^(G$5-$B$68+1),0) -> 0 | H77: =IF(H$5>=$B$68,$B$69*(1-Assumptions!$F$63)^(H$5-$B$68+1),0) -> 0 | I77: =IF(I$5>=$B$68,$B$69*(1-Assumptions!$F$63)^(I$5-$B$68+1),0) -> 0 | J77: =IF(J$5>=$B$68,$B$69*(1-Assumptions!$F$63)^(J$5-$B$68+1),0) -> 0 | ... L77: =IF(L$5>=$B$68,$B$69*(1-Assumptions!$F$63)^(L$5-$B$68+1),0) -> 0
A79: Aircraft #7
A80: Purchase year | B80: =2027+COUNTIF('Fleet Plan'!$C$9:$L$9,"<7") -> 2037
A81: Price paid | B81: =IF($B$80>2036,0,Assumptions!$F$7*(1+Assumptions!$F$8)^($B$80-2027)) -> 0
A82: Loan | B82: =$B$81*Assumptions!$F$16 -> 0
A83: Annual payment | B83: =IF($B$82=0,0,PMT(Assumptions!$F$17,Assumptions!$F$18,-$B$82)) -> 0
A84: Beginning balance | C84: =IF(C$5=$B$80,$B$82,IF(C$5>$B$80,0,0)) -> 0 | D84: =IF(D$5=$B$80,$B$82,IF(D$5>$B$80,C88,0)) -> 0 | E84: =IF(E$5=$B$80,$B$82,IF(E$5>$B$80,D88,0)) -> 0 | F84: =IF(F$5=$B$80,$B$82,IF(F$5>$B$80,E88,0)) -> 0 | G84: =IF(G$5=$B$80,$B$82,IF(G$5>$B$80,F88,0)) -> 0 | H84: =IF(H$5=$B$80,$B$82,IF(H$5>$B$80,G88,0)) -> 0 | I84: =IF(I$5=$B$80,$B$82,IF(I$5>$B$80,H88,0)) -> 0 | J84: =IF(J$5=$B$80,$B$82,IF(J$5>$B$80,I88,0)) -> 0 | K84: =IF(K$5=$B$80,$B$82,IF(K$5>$B$80,J88,0)) -> 0 | L84: =IF(L$5=$B$80,$B$82,IF(L$5>$B$80,K88,0)) -> 0
A85: Interest | C85: =C84*Assumptions!$F$17 -> 0 | D85: =D84*Assumptions!$F$17 -> 0 | E85: =E84*Assumptions!$F$17 -> 0 | F85: =F84*Assumptions!$F$17 -> 0 | G85: =G84*Assumptions!$F$17 -> 0 | H85: =H84*Assumptions!$F$17 -> 0 | I85: =I84*Assumptions!$F$17 -> 0 | J85: =J84*Assumptions!$F$17 -> 0 | ... L85: =L84*Assumptions!$F$17 -> 0
A86: Payment | C86: =IF(C84>0,MIN($B$83,C84+C85),0) -> 0 | D86: =IF(D84>0,MIN($B$83,D84+D85),0) -> 0 | E86: =IF(E84>0,MIN($B$83,E84+E85),0) -> 0 | F86: =IF(F84>0,MIN($B$83,F84+F85),0) -> 0 | G86: =IF(G84>0,MIN($B$83,G84+G85),0) -> 0 | H86: =IF(H84>0,MIN($B$83,H84+H85),0) -> 0 | I86: =IF(I84>0,MIN($B$83,I84+I85),0) -> 0 | J86: =IF(J84>0,MIN($B$83,J84+J85),0) -> 0 | ... L86: =IF(L84>0,MIN($B$83,L84+L85),0) -> 0
A87: Principal | C87: =C86-C85 -> 0 | D87: =D86-D85 -> 0 | E87: =E86-E85 -> 0 | F87: =F86-F85 -> 0 | G87: =G86-G85 -> 0 | H87: =H86-H85 -> 0 | I87: =I86-I85 -> 0 | J87: =J86-J85 -> 0 | ... L87: =L86-L85 -> 0
A88: Ending balance | C88: =C84-C87 -> 0 | D88: =D84-D87 -> 0 | E88: =E84-E87 -> 0 | F88: =F84-F87 -> 0 | G88: =G84-G87 -> 0 | H88: =H84-H87 -> 0 | I88: =I84-I87 -> 0 | J88: =J84-J87 -> 0 | ... L88: =L84-L87 -> 0
A89: Market value (year end) | C89: =IF(C$5>=$B$80,$B$81*(1-Assumptions!$F$63)^(C$5-$B$80+1),0) -> 0 | D89: =IF(D$5>=$B$80,$B$81*(1-Assumptions!$F$63)^(D$5-$B$80+1),0) -> 0 | E89: =IF(E$5>=$B$80,$B$81*(1-Assumptions!$F$63)^(E$5-$B$80+1),0) -> 0 | F89: =IF(F$5>=$B$80,$B$81*(1-Assumptions!$F$63)^(F$5-$B$80+1),0) -> 0 | G89: =IF(G$5>=$B$80,$B$81*(1-Assumptions!$F$63)^(G$5-$B$80+1),0) -> 0 | H89: =IF(H$5>=$B$80,$B$81*(1-Assumptions!$F$63)^(H$5-$B$80+1),0) -> 0 | I89: =IF(I$5>=$B$80,$B$81*(1-Assumptions!$F$63)^(I$5-$B$80+1),0) -> 0 | J89: =IF(J$5>=$B$80,$B$81*(1-Assumptions!$F$63)^(J$5-$B$80+1),0) -> 0 | ... L89: =IF(L$5>=$B$80,$B$81*(1-Assumptions!$F$63)^(L$5-$B$80+1),0) -> 0
A91: Fleet totals
A92: Total interest | C92: =C13+C25+C37+C49+C61+C73+C85 -> 783000 | D92: =D13+D25+D37+D49+D61+D73+D85 -> 752435.87 | E92: =E13+E25+E37+E49+E61+E73+E85 -> 719655.84 | F92: =F13+F25+F37+F49+F61+F73+F85 -> 1467499.3 | G92: =G13+G25+G37+G49+G61+G73+G85 -> 1399229.7 | H92: =H13+H25+H37+H49+H61+H73+H85 -> 1326010.6 | I92: =I13+I25+I37+I49+I61+I73+I85 -> 2030483.1 | J92: =J13+J25+J37+J49+J61+J73+J85 -> 1915698.2 | ... L92: =L13+L25+L37+L49+L61+L73+L85 -> 1660559.4
A93: Total principal | C93: =C15+C27+C39+C51+C63+C75+C87 -> 421574.23 | D93: =D15+D27+D39+D51+D63+D75+D87 -> 452138.36 | E93: =E15+E27+E39+E51+E63+E75+E87 -> 484918.39 | F93: =F15+F27+F39+F51+F63+F75+F87 -> 941649.2 | G93: =G15+G27+G39+G51+G63+G75+G87 -> 1009918.8 | H93: =H15+H27+H39+H51+H63+H75+H87 -> 1083137.9 | I93: =I15+I27+I39+I51+I63+I75+I87 -> 1583239.6 | J93: =J15+J27+J39+J51+J63+J75+J87 -> 1698024.5 | ... L93: =L15+L27+L39+L51+L63+L75+L87 -> 1953163.3
A94: Total debt outstanding | C94: =C16+C28+C40+C52+C64+C76+C88 -> 10378426 | D94: =D16+D28+D40+D52+D64+D76+D88 -> 9926287.4 | E94: =E16+E28+E40+E52+E64+E76+E88 -> 9441369 | F94: =F16+F28+F40+F52+F64+F76+F88 -> 19299720 | G94: =G16+G28+G40+G52+G64+G76+G88 -> 18289801 | H94: =H16+H28+H40+H52+H64+H76+H88 -> 17206663 | I94: =I16+I28+I40+I52+I64+I76+I88 -> 26423424 | J94: =J16+J28+J40+J52+J64+J76+J88 -> 24725399 | ... L94: =L16+L28+L40+L52+L64+L76+L88 -> 20951105
A95: Total fleet market value | C95: =C17+C29+C41+C53+C65+C77+C89 -> 12825000 | D95: =D17+D29+D41+D53+D65+D77+D89 -> 12183750 | E95: =E17+E29+E41+E53+E65+E77+E89 -> 11574562 | F95: =F17+F29+F41+F53+F65+F77+F89 -> 23820834 | G95: =G17+G29+G41+G53+G65+G77+G89 -> 22629793 | H95: =H17+H29+H41+H53+H65+H77+H89 -> 21498303 | I95: =I17+I29+I41+I53+I65+I77+I89 -> 33248388 | J95: =J17+J29+J41+J53+J65+J77+J89 -> 31585968 | ... L95: =L17+L29+L41+L53+L65+L77+L89 -> 28506337

Sheet Exit
A1: Exit valuation (Live scenario)
A2: Fleet sold at market, debt repaid, management platform sold at an EBITDA multiple.
A4: Item | C4: Value | D4: Note
A5: Exit year | C5: =Assumptions!$F$60 -> 2036
A6: Fleet market value | C6: =INDEX(Forecast!$C$59:$L$59,MATCH(Assumptions!$F$60,Forecast!$C$5:$L$5,0)) -> 28506337 | D6: Debt Schedule, year-end market value
A7: Less selling costs | C7: =-C6*Assumptions!$F$62 -> -570126.73
A8: Third-party management margin in exit year | C8: =INDEX(Forecast!$C$22:$L$22,MATCH(Assumptions!$F$60,Forecast!$C$5:$L$5,0)) -> 3000978.3 | D8: Recurring platform earnings
A9: Platform value (margin x multiple) | C9: =C8*Assumptions!$F$61 -> 18005870 | D9: Buyers pay for managed fleet and certificate
A10: Enterprise value | C10: =C6+C7+C9 -> 45942080
A11: Less debt outstanding | C11: =-INDEX(Forecast!$C$60:$L$60,MATCH(Assumptions!$F$60,Forecast!$C$5:$L$5,0)) -> -20951105
A12: Plus cash on hand | C12: =INDEX(Forecast!$C$55:$L$55,MATCH(Assumptions!$F$60,Forecast!$C$5:$L$5,0)) -> 6703368
A13: Equity value at exit (before tax) | C13: =SUM(C10:C12) -> 31694343
A14: Less illustrative tax on depreciation recapture | C14: =0 -> 0 | D14: Set to zero here: depends on Henry's tax position. See Forecast memo and talk to a CPA.
A15: Net exit proceeds to owners | C15: =C13+C14 -> 31694343
A17: Total owner equity contributed | C17: =SUMPRODUCT((Forecast!$C$5:$L$5<=Assumptions!$F$60)*Forecast!$C$54:$L$54) -> 17667996
A18: Multiple on invested equity (MOIC) | C18: =IF(C17=0,0,C15/C17) -> 1.7938844
A19: Equity IRR | C19: =IFERROR(IRR(Forecast!$C$72:$L$72),"n/a") -> 0.094001978 | D19: Ignores the tax memo; including usable tax losses would raise it.
A20: Peak cumulative equity | C20: =MAX(Forecast!$C$56:$L$56) -> 17667996 | D20: Cash Henry and partners must be able to fund
